Workbook

Sheet Instructions
A2: 0 | B2: Project Storm - Model Map, Method & Instructions
B4: How this model is built
B6: Assumptions | C6: Every input in one place. Blue cells are hardcoded; yellow cells are the levers worth flexing.
B7: Calcs | C7: Indices, the merit-order power price stack, revenue, opex, working capital, the senior debt schedule and the tax computation.
B8: Output | C8: P&L, cash flow, the valuation, the balance sheet and the sources & uses at close. Deliberately kept free of workings.
B9: Analysis | C9: The headline results and each supporting analysis (downside, exit, hedging, tax cap, sub-debt), with full workings alongside.
B10: Sensitivities | C10: The tables behind the recommendation, including the PPA analysis.
B13: Conventions
B14: Blue text | C14: Hardcoded input or scenario lever
B15: Black text | C15: Formula calculated on the same sheet
B16: Green text | C16: Link to another sheet
B17: Yellow fill | C17: Key assumption or solved lever
B18: Units | C18: All monetary amounts are in £'000 unless the unit column says otherwise. Prices are £/MWh, production is GWh, so GWh x £/MWh gives £'000 directly.
B20: The two solved cells
B21: Calcs!E105:P105 | C21: The sculpted senior principal profile. Debt size, the interest it bears and the tax it shelters are mutually dependent, so this profile is solved outside the sheet and entered as an input. Calcs!D100 proves the DSCR is a constant 1.30x and Calcs!D118 proves the amount drawn equals the amount the sizing test supports.
B23: Analysis!D131 | C23: The subordinated loan, solved the same way. Analysis!D165 is the check.
B25: Checks that must all read nil
B26: Output!E86:S86 | C26: Balance sheet balances in every year
B27: Output!D101 | C27: Sources equal uses at close
B28: Calcs!D118 | C28: Senior debt drawn equals the debt the sizing test supports
B29: Analysis!D165 | C29: Subordinated loan drawn equals the amount 1.20x DSCR supports
B31: Key observations
B32: - | C32: Electricity demand grows at 0.25% a year to 2015 and 0.5% thereafter (Assumptions row 23). CCGT keeps ample spare capacity above demand in every year, so the clearing plant is robust to the demand path.
B34: - | C34: The merit order flips in 2020: coal becomes dearer than CCGT, so coal sets the price for two years and the curve has a hump. This is why the stack has to be ranked dynamically rather than assumed.
B36: - | C36: Senior debt is capped by the 1.30x DSCR test at £51.2m, not by the 85% of fixed assets test, which would allow £57.4m. The gearing that results is 84% of enterprise value - high, and the reason the equity return is so sensitive to price.
B38: - | C38: The 30% interest deductibility cap never binds at this leverage, so it costs nothing in the base case.

Sheet Assumptions
A2: =Instructions!A2+1 -> 1 | B2: Project Storm - Assumptions
B4: Period End | D4: 41274 | E4: =EOMONTH(D4,year_months) -> 41639 | F4: =EOMONTH(E4,year_months) -> 42004 | G4: =EOMONTH(F4,year_months) -> 42369 | H4: =EOMONTH(G4,year_months) -> 42735 | I4: =EOMONTH(H4,year_months) -> 43100 | J4: =EOMONTH(I4,year_months) -> 43465 | K4: =EOMONTH(J4,year_months) -> 43830 | L4: =EOMONTH(K4,year_months) -> 44196 | ... S4: =EOMONTH(R4,year_months) -> 46752
B5: Calendar Year | D5: =YEAR(D4) -> 2012 | E5: =YEAR(E4) -> 2013 | F5: =YEAR(F4) -> 2014 | G5: =YEAR(G4) -> 2015 | H5: =YEAR(H4) -> 2016 | I5: =YEAR(I4) -> 2017 | J5: =YEAR(J4) -> 2018 | K5: =YEAR(K4) -> 2019 | ... S5: =YEAR(S4) -> 2027
B6: Model Year | D6: 0 | E6: =D6+1 -> 1 | F6: =E6+1 -> 2 | G6: =F6+1 -> 3 | H6: =G6+1 -> 4 | I6: =H6+1 -> 5 | J6: =I6+1 -> 6 | K6: =J6+1 -> 7 | L6: =K6+1 -> 8 | ... S6: =R6+1 -> 15
A8: =MAX($A$2:A7)+0.01 -> 1.01 | B8: General
B10: Hours in year | C10: [hours] | D10: 8760
B11: Months in Year | C11: [months] | D11: 12
A14: =MAX($A$2:A13)+0.01 -> 1.02 | B14: Economics
B16: CPI | C16: [%] | D16: 0.025 | E16: 0.025 | F16: 0.025 | G16: 0.025 | H16: 0.02 | I16: 0.02 | J16: 0.02 | K16: 0.02 | L16: 0.02 | M16: 0.02 | N16: 0.02 | O16: 0.02 | P16: 0.02 | Q16: 0.02 | R16: 0.02 | S16: 0.02 | U16: 2.5% to 2015 inclusive, 2.0% thereafter
B17: Libor | C17: [%] | D17: 0.00939 | E17: 0.0086301431 | F17: 0.0094860561 | G17: 0.012707946 | H17: 0.016694652 | I17: 0.020548944 | J17: 0.023015624 | K17: 0.024223962 | L17: 0.025343402 | M17: 0.025947203 | N17: 0.027337059 | O17: 0.027657667 | P17: 0.027657667 | Q17: 0.026492746 | R17: 0.026492746 | S17: 0.026492746 | U17: LIBOR curve as input; no interest income assumed
A20: =MAX($A$2:A19)+0.01 -> 1.03 | B20: Electricity Market
B22: Demand | C22: [TWh] | D22: 320 | E22: =D22*(1+E23) -> 320.8 | F22: =E22*(1+F23) -> 321.602 | G22: =F22*(1+G23) -> 322.406 | H22: =G22*(1+H23) -> 324.01804 | I22: =H22*(1+I23) -> 325.63813 | J22: =I22*(1+J23) -> 327.26632 | K22: =J22*(1+K23) -> 328.90265 | L22: =K22*(1+L23) -> 330.54716 | ... S22: =R22*(1+S23) -> 342.2913 | T22: << | U22: Demand grows at +0.25% p.a. to 2015 and +0.5% thereafter, driven by row 23.
B23: Demand Growth | C23: [%] | E23: 0.0025 | F23: 0.0025 | G23: 0.0025 | H23: 0.005 | I23: 0.005 | J23: 0.005 | K23: 0.005 | L23: 0.005 | M23: 0.005 | N23: 0.005 | O23: 0.005 | P23: 0.005 | Q23: 0.005 | R23: 0.005 | S23: 0.005
B24: Supply
B26: Average Installed Capacity Forecast
B27: Coal | C27: [GW] | D27: 35 | E27: 35 | F27: 35 | G27: 32.5 | H27: 30 | I27: 27.5 | J27: 25 | K27: 22.5 | L27: 20 | M27: 20 | N27: 20 | O27: 20 | P27: 15 | Q27: 15 | R27: 10 | S27: 0
B28: CCGT | C28: [GW] | D28: 55 | E28: 55 | F28: 55 | G28: 55 | H28: 55 | I28: 55 | J28: 55 | K28: 55 | L28: 57 | M28: 59 | N28: 61 | O28: 61 | P28: 61 | Q28: 61 | R28: 61 | S28: 61
B29: Renewables (incl. Hydro) | C29: [GW] | D29: 15 | E29: 15.45 | F29: 15.9135 | G29: 16.390905 | H29: 16.882632 | I29: 17.389111 | J29: 17.910784 | K29: 18.448108 | L29: 19.001551 | M29: 19.571598 | N29: 20.158746 | O29: 20.763508 | P29: 21.386413 | Q29: 22.028006 | R29: 22.688846 | S29: 23.369511
B31: Weighted Avg Capacity Factor
B32: =B27 -> Coal | C32: [%] | D32: 0.35 | E32: 0.34653465 | F32: 0.34310362 | G32: 0.33970655 | H32: 0.33634312 | I32: 0.33301299 | J32: 0.32971583 | K32: 0.3 | L32: 0.3 | M32: 0.3 | N32: 0.3 | O32: 0.3 | P32: 0.3 | Q32: 0.3 | R32: 0.3 | S32: 0.3
B33: =B28 -> CCGT | C33: [%] | D33: 0.5 | E33: 0.505 | F33: 0.51005 | G33: 0.5151505 | H33: 0.52030201 | I33: 0.52550503 | J33: 0.53076008 | K33: 0.53606768 | L33: 0.54142835 | M33: 0.54684264 | N33: 0.55231106 | O33: 0.55783417 | P33: 0.56341252 | Q33: 0.56904664 | R33: 0.57473711 | S33: 0.58048448
B34: =B29 -> Renewables (incl. Hydro) | C34: [%] | D34: 0.2 | E34: =D34*1.015 -> 0.203 | F34: =E34*1.015 -> 0.206045 | G34: =F34*1.015 -> 0.20913567 | H34: =G34*1.015 -> 0.21227271 | I34: =H34*1.015 -> 0.2154568 | J34: =I34*1.015 -> 0.21868865 | K34: =J34*1.015 -> 0.22196898 | L34: =K34*1.015 -> 0.22529852 | ... S34: =R34*1.015 -> 0.25004641
B36: Weighted Avg Marginal Cost | C36: [real - 2012]
B37: =B27 -> Coal | C37: [£/MWh - Real] | D37: 35 | E37: 35.35 | F37: 36.057 | G37: 37.13871 | H37: 38.624258 | I37: 40.555471 | J37: 42.9888 | K37: 45.998016 | L37: 49.677857 | M37: 50.671414 | N37: 51.684842 | O37: 52.718539 | P37: 53.77291 | Q37: 54.848368 | R37: 55.945335 | S37: 57.064242
B38: =B28 -> CCGT | C38: [£/MWh - Real] | D38: 55 | E38: 54.726368 | F38: 54.184523 | G38: 53.383766 | H38: 52.337026 | I38: 51.060513 | J38: 49.573314 | K38: 47.896921 | L38: 46.054732 | M38: 44.071514 | N38: 41.97287 | O38: 39.784711 | P38: 37.532747 | Q38: 35.242016 | R38: 32.936463 | S38: 30.63857
B39: =B29 -> Renewables (incl. Hydro) | C39: [£/MWh - Real] | D39: 5 | E39: 5 | F39: 5 | G39: 5 | H39: 5 | I39: 5 | J39: 5 | K39: 5 | L39: 5 | M39: 5 | N39: 5 | O39: 5 | P39: 5 | Q39: 5 | R39: 5 | S39: 5
B41: Hint: supply is always equal to demand; if possible try to make the pricing calculation dynamic (you may need to rank the supply)
A44: =MAX($A$2:A43)+0.01 -> 1.04 | B44: Operating Assumptions
B46: Generation
B47: Installed Capacity | C47: [MW] | D47: 50
B48: Load Factor - P75 | C48: [hours] | D48: 2500
B49: Load Factor - P90 | C49: [hours] | D49: 2350
B50: Production Case (1=P75, 2=P90, 3=P90 10y then P75) | C50: [#] | D50: 1
B51: Operations Start Date | C51: [date] | D51: 39448
B52: Residual Accounting & Economic Life | C52: [years] | D52: 15
B54: Regulated Subsidy
B55: Subsidy Price - 2012 | C55: [£/MWh] | D55: 40
B56: Subsidy Escalation (CPI - 1.5%) | C56: [%] | E56: =MAX(E16-E57,0) -> 0.01 | F56: =MAX(F16-F57,0) -> 0.01 | G56: =MAX(G16-G57,0) -> 0.01 | H56: =MAX(H16-H57,0) -> 0.005 | I56: =MAX(I16-I57,0) -> 0.005 | J56: =MAX(J16-J57,0) -> 0.005 | K56: =MAX(K16-K57,0) -> 0.005 | L56: =MAX(L16-L57,0) -> 0.005 | ... S56: =MAX(S16-S57,0) -> 0.005
B57: Subsidy Escalation Discount to CPI | C57: [%] | D57: 0.015 | E57: 0.015 | F57: 0.015 | G57: 0.015 | H57: 0.015 | I57: 0.015 | J57: 0.015 | K57: 0.015 | L57: 0.015 | M57: 0.015 | N57: 0.015 | O57: 0.015 | P57: 0.015 | Q57: 0.015 | R57: 0.015 | S57: 0.015
B58: Subsidy Tenor from Operations Start | C58: [years] | D58: 15
B59: Final Subsidy Year | C59: [year] | D59: =YEAR(D51)+D58-1 -> 2022
B61: Operating Costs
B62: Fixed Opex | C62: [£'000/MW] | D62: 50
B63: Variable Opex | C63: [£/MWh] | D63: 5
B64: Opex Escalation Premium to CPI | C64: [%] | D64: 0.0025 | E64: 0.0025 | F64: 0.0025 | G64: 0.0025 | H64: 0.0025 | I64: 0.0025 | J64: 0.0025 | K64: 0.0025 | L64: 0.0025 | M64: 0.0025 | N64: 0.0025 | O64: 0.0025 | P64: 0.0025 | Q64: 0.0025 | R64: 0.0025 | S64: 0.0025
B65: Opex Escalation (CPI + 0.25%) | C65: [%] | E65: =E16+E64 -> 0.0275 | F65: =F16+F64 -> 0.0275 | G65: =G16+G64 -> 0.0275 | H65: =H16+H64 -> 0.0225 | I65: =I16+I64 -> 0.0225 | J65: =J16+J64 -> 0.0225 | K65: =K16+K64 -> 0.0225 | L65: =L16+L64 -> 0.0225 | ... S65: =S16+S64 -> 0.0225
A67: =MAX($A$2:A66)+0.01 -> 1.05 | B67: Tax
B69: Corporate Income Tax Rate | C69: [%] | D69: 0.25
B70: Interest Deductibility Limit (% of EBITDA) | C70: [%] | D70: 0.3 | U70: Excess disallowed interest carried forward indefinitely
A72: =MAX($A$2:A71)+0.01 -> 1.06 | B72: Senior Debt
B74: Tenor | C74: [years] | D74: 12
B75: Margin | C75: [%] | D75: 0.03
B76: Upfront Fee | C76: [%] | D76: 0.02
B77: Max Gearing (% of Fixed Assets) | C77: [%] | D77: 0.85
B78: Minimum DSCR (on P75 generation) | C78: [x] | D78: 1.3
B79: Hedging Ratio (% of outstanding principal) | C79: [%] | D79: 0.85
B80: All-in Interest Rate (LIBOR + Margin) | C80: [%] | E80: =E17+$D$75 -> 0.038630143 | F80: =F17+$D$75 -> 0.039486056 | G80: =G17+$D$75 -> 0.042707946 | H80: =H17+$D$75 -> 0.046694652 | I80: =I17+$D$75 -> 0.050548944 | J80: =J17+$D$75 -> 0.053015624 | K80: =K17+$D$75 -> 0.054223962 | L80: =L17+$D$75 -> 0.055343402 | ... S80: =S17+$D$75 -> 0.056492746
A82: =MAX($A$2:A81)+0.01 -> 1.07 | B82: Subordinated Debt
B84: Tenor | C84: [years] | D84: 5
B85: Coupon | C85: [%] | D85: 0.09
B86: Minimum DSCR | C86: [x] | D86: 1.2
B87: Annuity Factor | C87: [x] | D87: =(1-(1+D85)^-D84)/D85 -> 3.8896513
A89: =MAX($A$2:A88)+0.01 -> 1.08 | B89: Transaction
B91: Transaction Date | C91: [date] | D91: 41274
B92: Transaction Costs (non-depreciable) | C92: [£'000] | D92: 500
B93: Target Buy & Hold Equity IRR | C93: [%] | D93: 0.12
B95: Exit Year | C95: [year] | D95: 2014
B96: Buyer's Required IRR at Exit | C96: [%] | D96: 0.11
B97: Exit Fee (% of Enterprise Value) | C97: [%] | D97: 0.0025
B99: Legend
B100: Blue text = hardcoded input / scenario lever
B101: Black text = formula on this sheet
B102: Green text = link to another sheet
B103: Yellow fill = key assumption or goal-seek lever

Sheet Calcs
A2: =Assumptions!A2+1 -> 2 | B2: Project Storm - Calculations
B4: Period End | D4: =timeline -> 41274 | E4: =timeline -> 41639 | F4: =timeline -> 42004 | G4: =timeline -> 42369 | H4: =timeline -> 42735 | I4: =timeline -> 43100 | J4: =timeline -> 43465 | K4: =timeline -> 43830 | ... S4: =timeline -> 46752
B5: Calendar Year | D5: =YEAR(D4) -> 2012 | E5: =YEAR(E4) -> 2013 | F5: =YEAR(F4) -> 2014 | G5: =YEAR(G4) -> 2015 | H5: =YEAR(H4) -> 2016 | I5: =YEAR(I4) -> 2017 | J5: =YEAR(J4) -> 2018 | K5: =YEAR(K4) -> 2019 | ... S5: =YEAR(S4) -> 2027
B6: Model Year | D6: 0 | E6: =D6+1 -> 1 | F6: =E6+1 -> 2 | G6: =F6+1 -> 3 | H6: =G6+1 -> 4 | I6: =H6+1 -> 5 | J6: =I6+1 -> 6 | K6: =J6+1 -> 7 | L6: =K6+1 -> 8 | ... S6: =R6+1 -> 15
B8: CPI Index | C8: [x] | D8: 1 | E8: =D8*(1+Assumptions!E16) -> 1.025 | F8: =E8*(1+Assumptions!F16) -> 1.050625 | G8: =F8*(1+Assumptions!G16) -> 1.0768906 | H8: =G8*(1+Assumptions!H16) -> 1.0984284 | I8: =H8*(1+Assumptions!I16) -> 1.120397 | J8: =I8*(1+Assumptions!J16) -> 1.1428049 | K8: =J8*(1+Assumptions!K16) -> 1.165661 | L8: =K8*(1+Assumptions!L16) -> 1.1889743 | ... S8: =R8*(1+Assumptions!S16) -> 1.3657577
B9: Cost Index (CPI + 0.25%) | C9: [x] | D9: 1 | E9: =D9*(1+Assumptions!E65) -> 1.0275 | F9: =E9*(1+Assumptions!F65) -> 1.0557562 | G9: =F9*(1+Assumptions!G65) -> 1.0847895 | H9: =G9*(1+Assumptions!H65) -> 1.1091973 | I9: =H9*(1+Assumptions!I65) -> 1.1341543 | J9: =I9*(1+Assumptions!J65) -> 1.1596727 | K9: =J9*(1+Assumptions!K65) -> 1.1857654 | L9: =K9*(1+Assumptions!L65) -> 1.2124451 | ... S9: =R9*(1+Assumptions!S65) -> 1.4167894
B10: Subsidy Index (CPI - 1.5%) | C10: [x] | D10: 1 | E10: =D10*(1+Assumptions!E56) -> 1.01 | F10: =E10*(1+Assumptions!F56) -> 1.0201 | G10: =F10*(1+Assumptions!G56) -> 1.030301 | H10: =G10*(1+Assumptions!H56) -> 1.0354525 | I10: =H10*(1+Assumptions!I56) -> 1.0406298 | J10: =I10*(1+Assumptions!J56) -> 1.0458329 | K10: =J10*(1+Assumptions!K56) -> 1.0510621 | L10: =K10*(1+Assumptions!L56) -> 1.0563174 | ... S10: =R10*(1+Assumptions!S56) -> 1.0938477
A11: =MAX($A$2:A9)+0.01 -> 2.01 | B11: Revenues
B13: Production
B15: P75 | C15: [GWh] | D15: =Assumptions!$D$47*Assumptions!$D$48/1000 -> 125 | E15: =Assumptions!$D$47*Assumptions!$D$48/1000 -> 125 | F15: =Assumptions!$D$47*Assumptions!$D$48/1000 -> 125 | G15: =Assumptions!$D$47*Assumptions!$D$48/1000 -> 125 | H15: =Assumptions!$D$47*Assumptions!$D$48/1000 -> 125 | I15: =Assumptions!$D$47*Assumptions!$D$48/1000 -> 125 | J15: =Assumptions!$D$47*Assumptions!$D$48/1000 -> 125 | K15: =Assumptions!$D$47*Assumptions!$D$48/1000 -> 125 | ... S15: =Assumptions!$D$47*Assumptions!$D$48/1000 -> 125
B16: P90 | C16: [GWh] | D16: =Assumptions!$D$47*Assumptions!$D$49/1000 -> 117.5 | E16: =Assumptions!$D$47*Assumptions!$D$49/1000 -> 117.5 | F16: =Assumptions!$D$47*Assumptions!$D$49/1000 -> 117.5 | G16: =Assumptions!$D$47*Assumptions!$D$49/1000 -> 117.5 | H16: =Assumptions!$D$47*Assumptions!$D$49/1000 -> 117.5 | I16: =Assumptions!$D$47*Assumptions!$D$49/1000 -> 117.5 | J16: =Assumptions!$D$47*Assumptions!$D$49/1000 -> 117.5 | K16: =Assumptions!$D$47*Assumptions!$D$49/1000 -> 117.5 | ... S16: =Assumptions!$D$47*Assumptions!$D$49/1000 -> 117.5
B17: Selected Scenario | C17: [GWh] | D17: =IF(Assumptions!$D$50=1,D15,IF(Assumptions!$D$50=2,D16,IF(D$5<=$D$5+10,D16,D15))) -> 125 | E17: =IF(Assumptions!$D$50=1,E15,IF(Assumptions!$D$50=2,E16,IF(E$5<=$D$5+10,E16,E15))) -> 125 | F17: =IF(Assumptions!$D$50=1,F15,IF(Assumptions!$D$50=2,F16,IF(F$5<=$D$5+10,F16,F15))) -> 125 | G17: =IF(Assumptions!$D$50=1,G15,IF(Assumptions!$D$50=2,G16,IF(G$5<=$D$5+10,G16,G15))) -> 125 | H17: =IF(Assumptions!$D$50=1,H15,IF(Assumptions!$D$50=2,H16,IF(H$5<=$D$5+10,H16,H15))) -> 125 | I17: =IF(Assumptions!$D$50=1,I15,IF(Assumptions!$D$50=2,I16,IF(I$5<=$D$5+10,I16,I15))) -> 125 | J17: =IF(Assumptions!$D$50=1,J15,IF(Assumptions!$D$50=2,J16,IF(J$5<=$D$5+10,J16,J15))) -> 125 | K17: =IF(Assumptions!$D$50=1,K15,IF(Assumptions!$D$50=2,K16,IF(K$5<=$D$5+10,K16,K15))) -> 125 | ... S17: =IF(Assumptions!$D$50=1,S15,IF(Assumptions!$D$50=2,S16,IF(S$5<=$D$5+10,S16,S15))) -> 125 | U17: Case 3 = P90 for the first 10 years (2013-22), P75 from 2023. 2012 shown at P75 for reference only - the buyer owns no 2012 economics.
B21: Power Prices
B23: Demand Index | C23: [x] | D23: =D24/$D$24 -> 1 | E23: =E24/$D$24 -> 1.0025 | F23: =F24/$D$24 -> 1.0050063 | G23: =G24/$D$24 -> 1.0075188 | H23: =H24/$D$24 -> 1.0125564 | I23: =I24/$D$24 -> 1.0176191 | J23: =J24/$D$24 -> 1.0227072 | K23: =K24/$D$24 -> 1.0278208 | ... S23: =S24/$D$24 -> 1.0696603
B24: Annual Demand | C24: [TWh] | D24: =Assumptions!D22 -> 320 | E24: =Assumptions!E22 -> 320.8 | F24: =Assumptions!F22 -> 321.602 | G24: =Assumptions!G22 -> 322.406 | H24: =Assumptions!H22 -> 324.01804 | I24: =Assumptions!I22 -> 325.63813 | J24: =Assumptions!J22 -> 327.26632 | K24: =Assumptions!K22 -> 328.90265 | ... S24: =Assumptions!S22 -> 342.2913
B26: Generation by Technology | C26: [TWh]
B27: Coal | C27: [TWh] | D27: =Assumptions!D27*Assumptions!D32*Assumptions!$D$10/1000 -> 107.31 | E27: =Assumptions!E27*Assumptions!E32*Assumptions!$D$10/1000 -> 106.24752 | F27: =Assumptions!F27*Assumptions!F32*Assumptions!$D$10/1000 -> 105.19557 | G27: =Assumptions!G27*Assumptions!G32*Assumptions!$D$10/1000 -> 96.714455 | H27: =Assumptions!H27*Assumptions!H32*Assumptions!$D$10/1000 -> 88.390972 | I27: =Assumptions!I27*Assumptions!I32*Assumptions!$D$10/1000 -> 80.222829 | J27: =Assumptions!J27*Assumptions!J32*Assumptions!$D$10/1000 -> 72.207767 | K27: =Assumptions!K27*Assumptions!K32*Assumptions!$D$10/1000 -> 59.13 | ... S27: =Assumptions!S27*Assumptions!S32*Assumptions!$D$10/1000 -> 0
B28: CCGT | C28: [TWh] | D28: =Assumptions!D28*Assumptions!D33*Assumptions!$D$10/1000 -> 240.9 | E28: =Assumptions!E28*Assumptions!E33*Assumptions!$D$10/1000 -> 243.309 | F28: =Assumptions!F28*Assumptions!F33*Assumptions!$D$10/1000 -> 245.74209 | G28: =Assumptions!G28*Assumptions!G33*Assumptions!$D$10/1000 -> 248.19951 | H28: =Assumptions!H28*Assumptions!H33*Assumptions!$D$10/1000 -> 250.68151 | I28: =Assumptions!I28*Assumptions!I33*Assumptions!$D$10/1000 -> 253.18832 | J28: =Assumptions!J28*Assumptions!J33*Assumptions!$D$10/1000 -> 255.7202 | K28: =Assumptions!K28*Assumptions!K33*Assumptions!$D$10/1000 -> 258.27741 | ... S28: =Assumptions!S28*Assumptions!S33*Assumptions!$D$10/1000 -> 310.18769
B29: Renewables | C29: [TWh] | D29: =Assumptions!D29*Assumptions!D34*Assumptions!$D$10/1000 -> 26.28 | E29: =Assumptions!E29*Assumptions!E34*Assumptions!$D$10/1000 -> 27.474426 | F29: =Assumptions!F29*Assumptions!F34*Assumptions!$D$10/1000 -> 28.723139 | G29: =Assumptions!G29*Assumptions!G34*Assumptions!$D$10/1000 -> 30.028605 | H29: =Assumptions!H29*Assumptions!H34*Assumptions!$D$10/1000 -> 31.393405 | I29: =Assumptions!I29*Assumptions!I34*Assumptions!$D$10/1000 -> 32.820236 | J29: =Assumptions!J29*Assumptions!J34*Assumptions!$D$10/1000 -> 34.311915 | K29: =Assumptions!K29*Assumptions!K34*Assumptions!$D$10/1000 -> 35.871392 | ... S29: =Assumptions!S29*Assumptions!S34*Assumptions!$D$10/1000 -> 51.188731
B30: Total Supply Available | C30: [TWh] | D30: =SUM(D27:D29) -> 374.49 | E30: =SUM(E27:E29) -> 377.03095 | F30: =SUM(F27:F29) -> 379.6608 | G30: =SUM(G27:G29) -> 374.94257 | H30: =SUM(H27:H29) -> 370.46588 | I30: =SUM(I27:I29) -> 366.23139 | J30: =SUM(J27:J29) -> 362.23989 | K30: =SUM(K27:K29) -> 353.2788 | ... S30: =SUM(S27:S29) -> 361.37642
B31: Surplus / (Deficit) vs Demand | C31: [TWh] | D31: =D30-D24 -> 54.49 | E31: =E30-E24 -> 56.230951 | F31: =F30-F24 -> 58.058798 | G31: =G30-G24 -> 52.536567 | H31: =H30-H24 -> 46.447848 | I31: =I30-I24 -> 40.593261 | J31: =J30-J24 -> 34.973571 | K31: =K30-K24 -> 24.376151 | ... S31: =S30-S24 -> 19.085115
B33: Marginal Cost - Real 2012 | C33: [£/MWh]
B34: Coal | C34: [£/MWh] | D34: =Assumptions!D37 -> 35 | E34: =Assumptions!E37 -> 35.35 | F34: =Assumptions!F37 -> 36.057 | G34: =Assumptions!G37 -> 37.13871 | H34: =Assumptions!H37 -> 38.624258 | I34: =Assumptions!I37 -> 40.555471 | J34: =Assumptions!J37 -> 42.9888 | K34: =Assumptions!K37 -> 45.998016 | ... S34: =Assumptions!S37 -> 57.064242
B35: CCGT | C35: [£/MWh] | D35: =Assumptions!D38 -> 55 | E35: =Assumptions!E38 -> 54.726368 | F35: =Assumptions!F38 -> 54.184523 | G35: =Assumptions!G38 -> 53.383766 | H35: =Assumptions!H38 -> 52.337026 | I35: =Assumptions!I38 -> 51.060513 | J35: =Assumptions!J38 -> 49.573314 | K35: =Assumptions!K38 -> 47.896921 | ... S35: =Assumptions!S38 -> 30.63857
B36: Renewables | C36: [£/MWh] | D36: =Assumptions!D39 -> 5 | E36: =Assumptions!E39 -> 5 | F36: =Assumptions!F39 -> 5 | G36: =Assumptions!G39 -> 5 | H36: =Assumptions!H39 -> 5 | I36: =Assumptions!I39 -> 5 | J36: =Assumptions!J39 -> 5 | K36: =Assumptions!K39 -> 5 | ... S36: =Assumptions!S39 -> 5
B38: Generation Cheaper than this Plant | C38: [TWh]
B39: Coal | C39: [TWh] | D39: =SUMPRODUCT((D$34:D$36<D34)*D$27:D$29) -> 26.28 | E39: =SUMPRODUCT((E$34:E$36<E34)*E$27:E$29) -> 27.474426 | F39: =SUMPRODUCT((F$34:F$36<F34)*F$27:F$29) -> 28.723139 | G39: =SUMPRODUCT((G$34:G$36<G34)*G$27:G$29) -> 30.028605 | H39: =SUMPRODUCT((H$34:H$36<H34)*H$27:H$29) -> 31.393405 | I39: =SUMPRODUCT((I$34:I$36<I34)*I$27:I$29) -> 32.820236 | J39: =SUMPRODUCT((J$34:J$36<J34)*J$27:J$29) -> 34.311915 | K39: =SUMPRODUCT((K$34:K$36<K34)*K$27:K$29) -> 35.871392 | ... S39: =SUMPRODUCT((S$34:S$36<S34)*S$27:S$29) -> 361.37642
B40: CCGT | C40: [TWh] | D40: =SUMPRODUCT((D$34:D$36<D35)*D$27:D$29) -> 133.59 | E40: =SUMPRODUCT((E$34:E$36<E35)*E$27:E$29) -> 133.72195 | F40: =SUMPRODUCT((F$34:F$36<F35)*F$27:F$29) -> 133.91871 | G40: =SUMPRODUCT((G$34:G$36<G35)*G$27:G$29) -> 126.74306 | H40: =SUMPRODUCT((H$34:H$36<H35)*H$27:H$29) -> 119.78438 | I40: =SUMPRODUCT((I$34:I$36<I35)*I$27:I$29) -> 113.04307 | J40: =SUMPRODUCT((J$34:J$36<J35)*J$27:J$29) -> 106.51968 | K40: =SUMPRODUCT((K$34:K$36<K35)*K$27:K$29) -> 95.001392 | ... S40: =SUMPRODUCT((S$34:S$36<S35)*S$27:S$29) -> 51.188731
B41: Renewables | C41: [TWh] | D41: =SUMPRODUCT((D$34:D$36<D36)*D$27:D$29) -> 0 | E41: =SUMPRODUCT((E$34:E$36<E36)*E$27:E$29) -> 0 | F41: =SUMPRODUCT((F$34:F$36<F36)*F$27:F$29) -> 0 | G41: =SUMPRODUCT((G$34:G$36<G36)*G$27:G$29) -> 0 | H41: =SUMPRODUCT((H$34:H$36<H36)*H$27:H$29) -> 0 | I41: =SUMPRODUCT((I$34:I$36<I36)*I$27:I$29) -> 0 | J41: =SUMPRODUCT((J$34:J$36<J36)*J$27:J$29) -> 0 | K41: =SUMPRODUCT((K$34:K$36<K36)*K$27:K$29) -> 0 | ... S41: =SUMPRODUCT((S$34:S$36<S36)*S$27:S$29) -> 0
B43: Marginal Plant Flag (1 = sets the price) | C43: [#]
B44: Coal | C44: [#] | D44: =IF(AND(D39<D$24,D39+D27>=D$24),1,0) -> 0 | E44: =IF(AND(E39<E$24,E39+E27>=E$24),1,0) -> 0 | F44: =IF(AND(F39<F$24,F39+F27>=F$24),1,0) -> 0 | G44: =IF(AND(G39<G$24,G39+G27>=G$24),1,0) -> 0 | H44: =IF(AND(H39<H$24,H39+H27>=H$24),1,0) -> 0 | I44: =IF(AND(I39<I$24,I39+I27>=I$24),1,0) -> 0 | J44: =IF(AND(J39<J$24,J39+J27>=J$24),1,0) -> 0 | K44: =IF(AND(K39<K$24,K39+K27>=K$24),1,0) -> 0 | ... S44: =IF(AND(S39<S$24,S39+S27>=S$24),1,0) -> 0
B45: CCGT | C45: [#] | D45: =IF(AND(D40<D$24,D40+D28>=D$24),1,0) -> 1 | E45: =IF(AND(E40<E$24,E40+E28>=E$24),1,0) -> 1 | F45: =IF(AND(F40<F$24,F40+F28>=F$24),1,0) -> 1 | G45: =IF(AND(G40<G$24,G40+G28>=G$24),1,0) -> 1 | H45: =IF(AND(H40<H$24,H40+H28>=H$24),1,0) -> 1 | I45: =IF(AND(I40<I$24,I40+I28>=I$24),1,0) -> 1 | J45: =IF(AND(J40<J$24,J40+J28>=J$24),1,0) -> 1 | K45: =IF(AND(K40<K$24,K40+K28>=K$24),1,0) -> 1 | ... S45: =IF(AND(S40<S$24,S40+S28>=S$24),1,0) -> 1
B46: Renewables | C46: [#] | D46: =IF(AND(D41<D$24,D41+D29>=D$24),1,0) -> 0 | E46: =IF(AND(E41<E$24,E41+E29>=E$24),1,0) -> 0 | F46: =IF(AND(F41<F$24,F41+F29>=F$24),1,0) -> 0 | G46: =IF(AND(G41<G$24,G41+G29>=G$24),1,0) -> 0 | H46: =IF(AND(H41<H$24,H41+H29>=H$24),1,0) -> 0 | I46: =IF(AND(I41<I$24,I41+I29>=I$24),1,0) -> 0 | J46: =IF(AND(J41<J$24,J41+J29>=J$24),1,0) -> 0 | K46: =IF(AND(K41<K$24,K41+K29>=K$24),1,0) -> 0 | ... S46: =IF(AND(S41<S$24,S41+S29>=S$24),1,0) -> 0
B47: Marginal Technology | C47: [text] | D47: =IF(D44=1,"Coal",IF(D45=1,"CCGT","Renewables")) -> CCGT | E47: =IF(E44=1,"Coal",IF(E45=1,"CCGT","Renewables")) -> CCGT | F47: =IF(F44=1,"Coal",IF(F45=1,"CCGT","Renewables")) -> CCGT | G47: =IF(G44=1,"Coal",IF(G45=1,"CCGT","Renewables")) -> CCGT | H47: =IF(H44=1,"Coal",IF(H45=1,"CCGT","Renewables")) -> CCGT | I47: =IF(I44=1,"Coal",IF(I45=1,"CCGT","Renewables")) -> CCGT | J47: =IF(J44=1,"Coal",IF(J45=1,"CCGT","Renewables")) -> CCGT | K47: =IF(K44=1,"Coal",IF(K45=1,"CCGT","Renewables")) -> CCGT | ... S47: =IF(S44=1,"Coal",IF(S45=1,"CCGT","Renewables")) -> CCGT
B48: Marginal Cost of Marginal Plant | C48: [£/MWh real] | D48: =SUMPRODUCT(D44:D46,D34:D36) -> 55 | E48: =SUMPRODUCT(E44:E46,E34:E36) -> 54.726368 | F48: =SUMPRODUCT(F44:F46,F34:F36) -> 54.184523 | G48: =SUMPRODUCT(G44:G46,G34:G36) -> 53.383766 | H48: =SUMPRODUCT(H44:H46,H34:H36) -> 52.337026 | I48: =SUMPRODUCT(I44:I46,I34:I36) -> 51.060513 | J48: =SUMPRODUCT(J44:J46,J34:J36) -> 49.573314 | K48: =SUMPRODUCT(K44:K46,K34:K36) -> 47.896921 | ... S48: =SUMPRODUCT(S44:S46,S34:S36) -> 30.63857
B49: Applicable Electricity Price | C49: [£/MWh] | D49: =D48*D8 -> 55 | E49: =E48*E8 -> 56.094527 | F49: =F48*F8 -> 56.927614 | G49: =G48*G8 -> 57.488478 | H49: =H48*H8 -> 57.488478 | I49: =I48*I8 -> 57.208046 | J49: =J48*J8 -> 56.652628 | K49: =K48*K8 -> 55.831575 | ... S49: =S48*S8 -> 41.844863
B50: Applicable Subsidy | C50: [£/MWh] | D50: =IF(D$5<=Assumptions!$D$59,Assumptions!$D$55*D10,0) -> 40 | E50: =IF(E$5<=Assumptions!$D$59,Assumptions!$D$55*E10,0) -> 40.4 | F50: =IF(F$5<=Assumptions!$D$59,Assumptions!$D$55*F10,0) -> 40.804 | G50: =IF(G$5<=Assumptions!$D$59,Assumptions!$D$55*G10,0) -> 41.21204 | H50: =IF(H$5<=Assumptions!$D$59,Assumptions!$D$55*H10,0) -> 41.4181 | I50: =IF(I$5<=Assumptions!$D$59,Assumptions!$D$55*I10,0) -> 41.625191 | J50: =IF(J$5<=Assumptions!$D$59,Assumptions!$D$55*J10,0) -> 41.833317 | K50: =IF(K$5<=Assumptions!$D$59,Assumptions!$D$55*K10,0) -> 42.042483 | ... S50: =IF(S$5<=Assumptions!$D$59,Assumptions!$D$55*S10,0) -> 0
B52: Revenue from Electricity | C52: [£'000] | D52: =D17*D49 -> 6875 | E52: =E17*E49 -> 7011.8159 | F52: =F17*F49 -> 7115.9518 | G52: =G17*G49 -> 7186.0597 | H52: =H17*H49 -> 7186.0597 | I52: =I17*I49 -> 7151.0058 | J52: =J17*J49 -> 7081.5785 | K52: =K17*K49 -> 6978.9469 | ... S52: =S17*S49 -> 5230.6079 | U52: GWh x £/MWh = £'000, so no unit conversion is needed here.
B53: Revenue from Subsidy | C53: [£'000] | D53: =D17*D50 -> 5000 | E53: =E17*E50 -> 5050 | F53: =F17*F50 -> 5100.5 | G53: =G17*G50 -> 5151.505 | H53: =H17*H50 -> 5177.2625 | I53: =I17*I50 -> 5203.1488 | J53: =J17*J50 -> 5229.1646 | K53: =K17*K50 -> 5255.3104 | ... S53: =S17*S50 -> 0
B54: Total Revenues | C54: [£'000] | D54: =SUM(D52:D53) -> 11875 | E54: =SUM(E52:E53) -> 12061.816 | F54: =SUM(F52:F53) -> 12216.452 | G54: =SUM(G52:G53) -> 12337.565 | H54: =SUM(H52:H53) -> 12363.322 | I54: =SUM(I52:I53) -> 12354.155 | J54: =SUM(J52:J53) -> 12310.743 | K54: =SUM(K52:K53) -> 12234.257 | ... S54: =SUM(S52:S53) -> 5230.6079
A58: =MAX($A$2:A57)+0.01 -> 2.02 | B58: Expenses
B60: Fixed Costs | C60: [£'000] | D60: =Assumptions!$D$62*Assumptions!$D$47*D9 -> 2500 | E60: =Assumptions!$D$62*Assumptions!$D$47*E9 -> 2568.75 | F60: =Assumptions!$D$62*Assumptions!$D$47*F9 -> 2639.3906 | G60: =Assumptions!$D$62*Assumptions!$D$47*G9 -> 2711.9739 | H60: =Assumptions!$D$62*Assumptions!$D$47*H9 -> 2772.9933 | I60: =Assumptions!$D$62*Assumptions!$D$47*I9 -> 2835.3856 | J60: =Assumptions!$D$62*Assumptions!$D$47*J9 -> 2899.1818 | K60: =Assumptions!$D$62*Assumptions!$D$47*K9 -> 2964.4134 | ... S60: =Assumptions!$D$62*Assumptions!$D$47*S9 -> 3541.9734
B61: Variable Costs | C61: [£'000] | D61: =Assumptions!$D$63*D17*D9 -> 625 | E61: =Assumptions!$D$63*E17*E9 -> 642.1875 | F61: =Assumptions!$D$63*F17*F9 -> 659.84766 | G61: =Assumptions!$D$63*G17*G9 -> 677.99347 | H61: =Assumptions!$D$63*H17*H9 -> 693.24832 | I61: =Assumptions!$D$63*I17*I9 -> 708.84641 | J61: =Assumptions!$D$63*J17*J9 -> 724.79545 | K61: =Assumptions!$D$63*K17*K9 -> 741.10335 | ... S61: =Assumptions!$D$63*S17*S9 -> 885.49336
B62: Total Operating Costs | C62: [£'000] | D62: =SUM(D60:D61) -> 3125 | E62: =SUM(E60:E61) -> 3210.9375 | F62: =SUM(F60:F61) -> 3299.2383 | G62: =SUM(G60:G61) -> 3389.9673 | H62: =SUM(H60:H61) -> 3466.2416 | I62: =SUM(I60:I61) -> 3544.232 | J62: =SUM(J60:J61) -> 3623.9773 | K62: =SUM(K60:K61) -> 3705.5167 | ... S62: =SUM(S60:S61) -> 4427.4668
B64: EBITDA | C64: [£'000] | D64: =D54-D62 -> 8750 | E64: =E54-E62 -> 8850.8784 | F64: =F54-F62 -> 8917.2135 | G64: =G54-G62 -> 8947.5974 | H64: =H54-H62 -> 8897.0806 | I64: =I54-I62 -> 8809.9226 | J64: =J54-J62 -> 8686.7658 | K64: =K54-K62 -> 8528.7406 | ... S64: =S54-S62 -> 803.14112
B65: EBITDA Margin | C65: [%] | D65: =IF(D54=0,0,D64/D54) -> 0.73684211 | E65: =IF(E54=0,0,E64/E54) -> 0.73379319 | F65: =IF(F54=0,0,F64/F54) -> 0.72993482 | G65: =IF(G54=0,0,G64/G54) -> 0.72523205 | H65: =IF(H54=0,0,H64/H54) -> 0.7196351 | I65: =IF(I54=0,0,I64/I54) -> 0.71311416 | J65: =IF(J54=0,0,J64/J54) -> 0.70562482 | K65: =IF(K54=0,0,K64/K54) -> 0.6971196 | ... S65: =IF(S54=0,0,S64/S54) -> 0.15354642
B67: Depreciation Charge | C67: [£'000] | E67: =Output!$D$76/Assumptions!$D$52 -> 4500 | F67: =Output!$D$76/Assumptions!$D$52 -> 4500 | G67: =Output!$D$76/Assumptions!$D$52 -> 4500 | H67: =Output!$D$76/Assumptions!$D$52 -> 4500 | I67: =Output!$D$76/Assumptions!$D$52 -> 4500 | J67: =Output!$D$76/Assumptions!$D$52 -> 4500 | K67: =Output!$D$76/Assumptions!$D$52 -> 4500 | L67: =Output!$D$76/Assumptions!$D$52 -> 4500 | ... S67: =Output!$D$76/Assumptions!$D$52 -> 4500
A71: =MAX($A$2:A70)+0.01 -> 2.03 | B71: Working Capital
B73: Receivable Days (calibrated to opening balance sheet) | C73: [days] | D73: =Output!$D$75/$D$54*365 -> 36.884211 | E73: =$D$73 -> 36.884211 | F73: =$D$73 -> 36.884211 | G73: =$D$73 -> 36.884211 | H73: =$D$73 -> 36.884211 | I73: =$D$73 -> 36.884211 | J73: =$D$73 -> 36.884211 | K73: =$D$73 -> 36.884211 | L73: =$D$73 -> 36.884211 | ... S73: =$D$73 -> 36.884211 | U73: Days are reverse-engineered from the opening balance sheet provided (receivables 1,200 on 2012 revenue; payables 300 on 2012 costs) and held flat.
B74: Payable Days (calibrated to opening balance sheet) | C74: [days] | D74: =Output!$D$81/$D$62*365 -> 35.04 | E74: =$D$74 -> 35.04 | F74: =$D$74 -> 35.04 | G74: =$D$74 -> 35.04 | H74: =$D$74 -> 35.04 | I74: =$D$74 -> 35.04 | J74: =$D$74 -> 35.04 | K74: =$D$74 -> 35.04 | L74: =$D$74 -> 35.04 | ... S74: =$D$74 -> 35.04
B76: Receivables | C76: [£'000] | D76: =D54*D73/365 -> 1200 | E76: =E54*E73/365 -> 1218.8782 | F76: =F54*F73/365 -> 1234.5046 | G76: =G54*G73/365 -> 1246.7434 | H76: =H54*H73/365 -> 1249.3462 | I76: =I54*I73/365 -> 1248.4198 | J76: =J54*J73/365 -> 1244.033 | K76: =K54*K73/365 -> 1236.3039 | ... S76: =S54*S73/365 -> 528.56669
B77: Payables | C77: [£'000] | D77: =D62*D74/365 -> 300 | E77: =E62*E74/365 -> 308.25 | F77: =F62*F74/365 -> 316.72688 | G77: =G62*G74/365 -> 325.43686 | H77: =H62*H74/365 -> 332.75919 | I77: =I62*I74/365 -> 340.24628 | J77: =J62*J74/365 -> 347.90182 | K77: =K62*K74/365 -> 355.72961 | ... S77: =S62*S74/365 -> 425.03681
B78: Net Working Capital | C78: [£'000] | D78: =D76-D77 -> 900 | E78: =E76-E77 -> 910.62824 | F78: =F76-F77 -> 917.77773 | G78: =G76-G77 -> 921.30652 | H78: =H76-H77 -> 916.58705 | I78: =I76-I77 -> 908.17356 | J78: =J76-J77 -> 896.13117 | K78: =K76-K77 -> 880.57429 | ... S78: =S76-S77 -> 103.52988
B79: Movement in Working Capital (cash impact) | C79: [£'000] | E79: =-(E78-D78) -> -10.62824 | F79: =-(F78-E78) -> -7.1494876 | G79: =-(G78-F78) -> -3.5287882 | H79: =-(H78-G78) -> 4.7194638 | I79: =-(I78-H78) -> 8.4134957 | J79: =-(J78-I78) -> 12.042387 | K79: =-(K78-J78) -> 15.556877 | L79: =-(L78-K78) -> -35.503414 | ... S79: =-(S78-R78) -> 37.854034
A96: =MAX($A$2:A95)+0.01 -> 2.04 | B96: Debt
B98: Senior Debt Drawn | C98: [£'000] | D98: =SUM(E105:S105) -> 51242.479
B99: Upfront Fee | C99: [£'000] | D99: =D98*Assumptions!$D$76 -> 1024.8496
B100: Minimum DSCR Achieved | C100: [x] | D100: =MIN(E110:P110) -> 1.3
B102: Opening Balance | C102: [£'000] | E102: =IF(E$6<=Assumptions!$D$74,D106,0) -> 51242.479 | F102: =IF(F$6<=Assumptions!$D$74,E106,0) -> 46861.4 | G102: =IF(G$6<=Assumptions!$D$74,F106,0) -> 42335.076 | H102: =IF(H$6<=Assumptions!$D$74,G106,0) -> 37754.25 | I102: =IF(I$6<=Assumptions!$D$74,H106,0) -> 33159.778 | J102: =IF(J$6<=Assumptions!$D$74,I106,0) -> 28542.698 | K102: =IF(K$6<=Assumptions!$D$74,J106,0) -> 23862.237 | L102: =IF(L$6<=Assumptions!$D$74,K106,0) -> 19093.112 | ... S102: =IF(S$6<=Assumptions!$D$74,R106,0) -> 0
B103: Interest | C103: [£'000] | E103: =E102*Assumptions!E80 -> 1979.5043 | F103: =F102*Assumptions!F80 -> 1850.3719 | G103: =G102*Assumptions!G80 -> 1808.0442 | H103: =H102*Assumptions!H80 -> 1762.9216 | I103: =I102*Assumptions!I80 -> 1676.1918 | J103: =J102*Assumptions!J80 -> 1513.2089 | K103: =K102*Assumptions!K80 -> 1293.905 | L103: =L102*Assumptions!L80 -> 1056.6778 | ... S103: =S102*Assumptions!S80 -> 0
B104: Debt Service | C104: [£'000] | E104: =E103+E105 -> 6360.5828 | F104: =F103+F105 -> 6376.6959 | G104: =G103+G105 -> 6388.8702 | H104: =H103+H105 -> 6357.3934 | I104: =I103+I105 -> 6293.2726 | J104: =J103+J105 -> 6193.6693 | K104: =K103+K105 -> 6063.0305 | L104: =L103+L105 -> 6178.4214 | ... S104: =S103+S105 -> 0
B105: Principal Repayment (sculpted profile) | C105: [£'000] | E105: 4381.0785 | F105: 4526.324 | G105: 4580.8261 | H105: 4594.4718 | I105: 4617.0808 | J105: 4680.4603 | K105: 4769.1254 | L105: 5121.7437 | M105: 5490.3792 | N105: 5122.5671 | O105: 1955.3877 | P105: 1403.0341 | Q105: 0 | R105: 0 | S105: 0 | U105: Sizing lever. The debt quantum, the interest it bears and the tax it shelters are mutually dependent, so the sculpted repayment profile is entered as an input and proved by the checks in D100 (DSCR a constant 1.30x) and D118 (drawn amount equals the sized amount). Re-solve these two if any assumption changes.
B106: Closing Balance | C106: [£'000] | D106: =D98 -> 51242.479 | E106: =E102-E105 -> 46861.4 | F106: =F102-F105 -> 42335.076 | G106: =G102-G105 -> 37754.25 | H106: =H102-H105 -> 33159.778 | I106: =I102-I105 -> 28542.698 | J106: =J102-J105 -> 23862.237 | K106: =K102-K105 -> 19093.112 | L106: =L102-L105 -> 13971.368 | ... S106: =S102-S105 -> 0
B107: Upfront Fee Amortisation | C107: [£'000] | E107: =IF(E$6<=Assumptions!$D$74,$D$99/Assumptions!$D$74,0) -> 85.404131 | F107: =IF(F$6<=Assumptions!$D$74,$D$99/Assumptions!$D$74,0) -> 85.404131 | G107: =IF(G$6<=Assumptions!$D$74,$D$99/Assumptions!$D$74,0) -> 85.404131 | H107: =IF(H$6<=Assumptions!$D$74,$D$99/Assumptions!$D$74,0) -> 85.404131 | I107: =IF(I$6<=Assumptions!$D$74,$D$99/Assumptions!$D$74,0) -> 85.404131 | J107: =IF(J$6<=Assumptions!$D$74,$D$99/Assumptions!$D$74,0) -> 85.404131 | K107: =IF(K$6<=Assumptions!$D$74,$D$99/Assumptions!$D$74,0) -> 85.404131 | L107: =IF(L$6<=Assumptions!$D$74,$D$99/Assumptions!$D$74,0) -> 85.404131 | ... S107: =IF(S$6<=Assumptions!$D$74,$D$99/Assumptions!$D$74,0) -> 0
B109: CFADS (EBITDA less tax paid, after working capital) | C109: [£'000] | E109: =E64-E145+E79 -> 8268.7577 | F109: =F64-F145+F79 -> 8289.7047 | G109: =G64-G145+G79 -> 8305.5313 | H109: =H64-H145+H79 -> 8264.6114 | I109: =I64-I145+I79 -> 8181.2544 | J109: =J64-J145+J79 -> 8051.77 | K109: =K64-K145+K79 -> 7881.9396 | L109: =L64-L145+L79 -> 8031.9479 | ... S109: =S64-S145+S79 -> 840.99515
B110: DSCR | C110: [x] | E110: =IF(E104=0,"n/a",E109/E104) -> 1.3 | F110: =IF(F104=0,"n/a",F109/F104) -> 1.3 | G110: =IF(G104=0,"n/a",G109/G104) -> 1.3 | H110: =IF(H104=0,"n/a",H109/H104) -> 1.3 | I110: =IF(I104=0,"n/a",I109/I104) -> 1.3 | J110: =IF(J104=0,"n/a",J109/J104) -> 1.3 | K110: =IF(K104=0,"n/a",K109/K104) -> 1.3 | L110: =IF(L104=0,"n/a",L109/L104) -> 1.3 | ... S110: =IF(S104=0,"n/a",S109/S104) -> n/a
B112: Debt Sizing
B113: Discount Factor at All-in Rate | C113: [x] | E113: =IF(E$6<=Assumptions!$D$74,1/(1+Assumptions!E80),0) -> 0.96280664 | F113: =IF(F$6<=Assumptions!$D$74,E113/(1+Assumptions!F80),0) -> 0.92623334 | G113: =IF(G$6<=Assumptions!$D$74,F113/(1+Assumptions!G80),0) -> 0.88829604 | H113: =IF(H$6<=Assumptions!$D$74,G113/(1+Assumptions!H80),0) -> 0.84866779 | I113: =IF(I$6<=Assumptions!$D$74,H113/(1+Assumptions!I80),0) -> 0.8078327 | J113: =IF(J$6<=Assumptions!$D$74,I113/(1+Assumptions!J80),0) -> 0.76716117 | K113: =IF(K$6<=Assumptions!$D$74,J113/(1+Assumptions!K80),0) -> 0.72770227 | L113: =IF(L$6<=Assumptions!$D$74,K113/(1+Assumptions!L80),0) -> 0.68954074 | M113: =IF(M$6<=Assumptions!$D$74,L113/(1+Assumptions!M80),0) -> 0.65300684 | ... S113: =IF(S$6<=Assumptions!$D$74,R113/(1+Assumptions!S80),0) -> 0
B114: PV of CFADS | C114: [£'000] | E114: =E109*E113 -> 7961.2148 | F114: =F109*F113 -> 7678.2008 | G114: =G109*G113 -> 7377.7706 | H114: =H109*H113 -> 7013.9095 | I114: =I109*I113 -> 6609.0848 | J114: =J109*J113 -> 6177.0054 | K114: =K109*K113 -> 5735.7054 | L114: =L109*L113 -> 5538.3553 | ... S114: =S109*S113 -> 0
B115: Maximum Debt at Minimum DSCR | C115: [£'000] | D115: =SUM(E114:S114)/Assumptions!$D$78 -> 51242.479
B116: Maximum Debt at 85% of Fixed Assets | C116: [£'000] | D116: =Assumptions!$D$77*Output!$D$76 -> 57375
B117: Sized Debt (lower of the two) | C117: [£'000] | D117: =MIN(D115,D116) -> 51242.479
B118: Check: Input less Sized Debt (must be nil) | C118: [£'000] | D118: =D98-D117 -> -1.162698e-07
B119: Binding Constraint | C119: [text] | D119: =IF(D116<D115,"85% of fixed assets","DSCR floor") -> DSCR floor
B120: Hedging and Swap Pricing
B121: Hedged Notional (85% of opening principal) | C121: [£'000] | E121: =Assumptions!$D$79*E102 -> 43556.107 | F121: =Assumptions!$D$79*F102 -> 39832.19 | G121: =Assumptions!$D$79*G102 -> 35984.815 | H121: =Assumptions!$D$79*H102 -> 32091.113 | I121: =Assumptions!$D$79*I102 -> 28185.812 | J121: =Assumptions!$D$79*J102 -> 24261.293 | K121: =Assumptions!$D$79*K102 -> 20282.902 | L121: =Assumptions!$D$79*L102 -> 16229.145 | ... S121: =Assumptions!$D$79*S102 -> 0
B122: Discount Factor at LIBOR | C122: [x] | E122: =IF(E$6<=Assumptions!$D$74,1/(1+Assumptions!E17),0) -> 0.9914437 | F122: =IF(F$6<=Assumptions!$D$74,E122/(1+Assumptions!F17),0) -> 0.98212719 | G122: =IF(G$6<=Assumptions!$D$74,F122/(1+Assumptions!G17),0) -> 0.96980298 | H122: =IF(H$6<=Assumptions!$D$74,G122/(1+Assumptions!H17),0) -> 0.95387831 | I122: =IF(I$6<=Assumptions!$D$74,H122/(1+Assumptions!I17),0) -> 0.9346718 | J122: =IF(J$6<=Assumptions!$D$74,I122/(1+Assumptions!J17),0) -> 0.91364372 | K122: =IF(K$6<=Assumptions!$D$74,J122/(1+Assumptions!K17),0) -> 0.89203509 | L122: =IF(L$6<=Assumptions!$D$74,K122/(1+Assumptions!L17),0) -> 0.86998667 | M122: =IF(M$6<=Assumptions!$D$74,L122/(1+Assumptions!M17),0) -> 0.84798386 | ... S122: =IF(S$6<=Assumptions!$D$74,R122/(1+Assumptions!S17),0) -> 0
B123: Floating Leg (Notional x LIBOR x DF) | C123: [£'000] | E123: =E121*Assumptions!E17*E122 -> 372.67916 | F123: =F121*Assumptions!F17*F122 -> 371.09714 | G123: =G121*Assumptions!G17*G122 -> 443.48421 | H123: =H121*Assumptions!H17*H122 -> 511.04028 | I123: =I121*Assumptions!I17*I122 -> 541.35131 | J123: =J121*Assumptions!J17*J122 -> 510.16841 | K123: =K121*Assumptions!K17*K122 -> 438.28559 | L123: =L121*Assumptions!L17*L122 -> 357.82704 | ... S123: =S121*Assumptions!S17*S122 -> 0
B124: Fixed Leg Basis (Notional x DF) | C124: [£'000] | E124: =E121*E122 -> 43183.428 | F124: =F121*F122 -> 39120.277 | G124: =G121*G122 -> 34898.181 | H124: =H121*H122 -> 30611.016 | I124: =I121*I122 -> 26344.483 | J124: =J121*J122 -> 22166.178 | K124: =K121*K122 -> 18093.06 | L124: =L121*L122 -> 14119.14 | ... S124: =S121*S122 -> 0
A125: =MAX($A$2:A124)+0.01 -> 2.05 | B125: Tax
B127: EBITDA | C127: [£'000] | E127: =E64 -> 8850.8784 | F127: =F64 -> 8917.2135 | G127: =G64 -> 8947.5974 | H127: =H64 -> 8897.0806 | I127: =I64 -> 8809.9226 | J127: =J64 -> 8686.7658 | K127: =K64 -> 8528.7406 | L127: =L64 -> 8875.9078 | ... S127: =S64 -> 803.14112
B128: Depreciation | C128: [£'000] | E128: =E67 -> 4500 | F128: =F67 -> 4500 | G128: =G67 -> 4500 | H128: =H67 -> 4500 | I128: =I67 -> 4500 | J128: =J67 -> 4500 | K128: =K67 -> 4500 | L128: =L67 -> 4500 | ... S128: =S67 -> 4500
B129: Senior Interest | C129: [£'000] | E129: =E103 -> 1979.5043 | F129: =F103 -> 1850.3719 | G129: =G103 -> 1808.0442 | H129: =H103 -> 1762.9216 | I129: =I103 -> 1676.1918 | J129: =J103 -> 1513.2089 | K129: =K103 -> 1293.905 | L129: =L103 -> 1056.6778 | ... S129: =S103 -> 0
B130: Upfront Fee Amortisation | C130: [£'000] | E130: =E107 -> 85.404131 | F130: =F107 -> 85.404131 | G130: =G107 -> 85.404131 | H130: =H107 -> 85.404131 | I130: =I107 -> 85.404131 | J130: =J107 -> 85.404131 | K130: =K107 -> 85.404131 | L130: =L107 -> 85.404131 | ... S130: =S107 -> 0
B131: Total Financing Costs | C131: [£'000] | E131: =SUM(E129:E130) -> 2064.9084 | F131: =SUM(F129:F130) -> 1935.776 | G131: =SUM(G129:G130) -> 1893.4483 | H131: =SUM(H129:H130) -> 1848.3257 | I131: =SUM(I129:I130) -> 1761.5959 | J131: =SUM(J129:J130) -> 1598.613 | K131: =SUM(K129:K130) -> 1379.3092 | L131: =SUM(L129:L130) -> 1142.0819 | ... S131: =SUM(S129:S130) -> 0
B133: Interest Deductibility Cap (30% of EBITDA) | C133: [£'000] | E133: =Assumptions!$D$70*MAX(E127,0) -> 2655.2635 | F133: =Assumptions!$D$70*MAX(F127,0) -> 2675.1641 | G133: =Assumptions!$D$70*MAX(G127,0) -> 2684.2792 | H133: =Assumptions!$D$70*MAX(H127,0) -> 2669.1242 | I133: =Assumptions!$D$70*MAX(I127,0) -> 2642.9768 | J133: =Assumptions!$D$70*MAX(J127,0) -> 2606.0298 | K133: =Assumptions!$D$70*MAX(K127,0) -> 2558.6222 | L133: =Assumptions!$D$70*MAX(L127,0) -> 2662.7723 | ... S133: =Assumptions!$D$70*MAX(S127,0) -> 240.94233
B134: Disallowed Interest Brought Forward | C134: [£'000] | E134: =D139 -> 0 | F134: =E139 -> 0 | G134: =F139 -> 0 | H134: =G139 -> 0 | I134: =H139 -> 0 | J134: =I139 -> 0 | K134: =J139 -> 0 | L134: =K139 -> 0 | ... S134: =R139 -> 0
B135: Allowed - Current Year | C135: [£'000] | E135: =MIN(E131,E133) -> 2064.9084 | F135: =MIN(F131,F133) -> 1935.776 | G135: =MIN(G131,G133) -> 1893.4483 | H135: =MIN(H131,H133) -> 1848.3257 | I135: =MIN(I131,I133) -> 1761.5959 | J135: =MIN(J131,J133) -> 1598.613 | K135: =MIN(K131,K133) -> 1379.3092 | L135: =MIN(L131,L133) -> 1142.0819 | ... S135: =MIN(S131,S133) -> 0
B136: Spare Capacity | C136: [£'000] | E136: =MAX(E133-E131,0) -> 590.35511 | F136: =MAX(F133-F131,0) -> 739.38804 | G136: =MAX(G133-G131,0) -> 790.83092 | H136: =MAX(H133-H131,0) -> 820.79847 | I136: =MAX(I133-I131,0) -> 881.38085 | J136: =MAX(J133-J131,0) -> 1007.4167 | K136: =MAX(K133-K131,0) -> 1179.313 | L136: =MAX(L133-L131,0) -> 1520.6904 | ... S136: =MAX(S133-S131,0) -> 240.94233
B137: Utilisation of Brought-forward Disallowed Interest | C137: [£'000] | E137: =MIN(E134,E136) -> 0 | F137: =MIN(F134,F136) -> 0 | G137: =MIN(G134,G136) -> 0 | H137: =MIN(H134,H136) -> 0 | I137: =MIN(I134,I136) -> 0 | J137: =MIN(J134,J136) -> 0 | K137: =MIN(K134,K136) -> 0 | L137: =MIN(L134,L136) -> 0 | ... S137: =MIN(S134,S136) -> 0
B138: Total Interest Allowed | C138: [£'000] | E138: =E135+E137 -> 2064.9084 | F138: =F135+F137 -> 1935.776 | G138: =G135+G137 -> 1893.4483 | H138: =H135+H137 -> 1848.3257 | I138: =I135+I137 -> 1761.5959 | J138: =J135+J137 -> 1598.613 | K138: =K135+K137 -> 1379.3092 | L138: =L135+L137 -> 1142.0819 | ... S138: =S135+S137 -> 0
B139: Disallowed Interest Carried Forward | C139: [£'000] | D139: 0 | E139: =E134+MAX(E131-E133,0)-E137 -> 0 | F139: =F134+MAX(F131-F133,0)-F137 -> 0 | G139: =G134+MAX(G131-G133,0)-G137 -> 0 | H139: =H134+MAX(H131-H133,0)-H137 -> 0 | I139: =I134+MAX(I131-I133,0)-I137 -> 0 | J139: =J134+MAX(J131-J133,0)-J137 -> 0 | K139: =K134+MAX(K131-K133,0)-K137 -> 0 | L139: =L134+MAX(L131-L133,0)-L137 -> 0 | ... S139: =S134+MAX(S131-S133,0)-S137 -> 0
B141: Profit Before Tax | C141: [£'000] | E141: =E127-E128-E138 -> 2285.97 | F141: =F127-F128-F138 -> 2481.4375 | G141: =G127-G128-G138 -> 2554.1491 | H141: =H127-H128-H138 -> 2548.7549 | I141: =I127-I128-I138 -> 2548.3266 | J141: =J127-J128-J138 -> 2588.1528 | K141: =K127-K128-K138 -> 2649.4314 | L141: =L127-L128-L138 -> 3233.8259 | ... S141: =S127-S128-S138 -> -3696.8589
B142: Tax Losses Brought Forward | C142: [£'000] | E142: =D144 -> 0 | F142: =E144 -> 0 | G142: =F144 -> 0 | H142: =G144 -> 0 | I142: =H144 -> 0 | J142: =I144 -> 0 | K142: =J144 -> 0 | L142: =K144 -> 0 | ... S142: =R144 -> 11593.83
B143: Taxable Profit | C143: [£'000] | E143: =MAX(E141-E142,0) -> 2285.97 | F143: =MAX(F141-F142,0) -> 2481.4375 | G143: =MAX(G141-G142,0) -> 2554.1491 | H143: =MAX(H141-H142,0) -> 2548.7549 | I143: =MAX(I141-I142,0) -> 2548.3266 | J143: =MAX(J141-J142,0) -> 2588.1528 | K143: =MAX(K141-K142,0) -> 2649.4314 | L143: =MAX(L141-L142,0) -> 3233.8259 | ... S143: =MAX(S141-S142,0) -> 0
B144: Tax Losses Carried Forward | C144: [£'000] | D144: 0 | E144: =MAX(E142-E141,0) -> 0 | F144: =MAX(F142-F141,0) -> 0 | G144: =MAX(G142-G141,0) -> 0 | H144: =MAX(H142-H141,0) -> 0 | I144: =MAX(I142-I141,0) -> 0 | J144: =MAX(J142-J141,0) -> 0 | K144: =MAX(K142-K141,0) -> 0 | L144: =MAX(L142-L141,0) -> 0 | ... S144: =MAX(S142-S141,0) -> 15290.689
B145: Tax Charge | C145: [£'000] | E145: =E143*Assumptions!$D$69 -> 571.4925 | F145: =F143*Assumptions!$D$69 -> 620.35938 | G145: =G143*Assumptions!$D$69 -> 638.53727 | H145: =H143*Assumptions!$D$69 -> 637.18873 | I145: =I143*Assumptions!$D$69 -> 637.08166 | J145: =J143*Assumptions!$D$69 -> 647.0382 | K145: =K143*Assumptions!$D$69 -> 662.35786 | L145: =L143*Assumptions!$D$69 -> 808.45647 | ... S145: =S143*Assumptions!$D$69 -> 0

Sheet Output
A2: =Calcs!A2+1 -> 3 | B2: Project Storm - Financial Statements & Valuation
B4: Period End | D4: =timeline -> 41274 | E4: =timeline -> 41639 | F4: =timeline -> 42004 | G4: =timeline -> 42369 | H4: =timeline -> 42735 | I4: =timeline -> 43100 | J4: =timeline -> 43465 | K4: =timeline -> 43830 | ... S4: =timeline -> 46752
B5: Calendar Year | D5: =YEAR(D4) -> 2012 | E5: =YEAR(E4) -> 2013 | F5: =YEAR(F4) -> 2014 | G5: =YEAR(G4) -> 2015 | H5: =YEAR(H4) -> 2016 | I5: =YEAR(I4) -> 2017 | J5: =YEAR(J4) -> 2018 | K5: =YEAR(K4) -> 2019 | ... S5: =YEAR(S4) -> 2027
B6: Model Year | D6: 0 | E6: =D6+1 -> 1 | F6: =E6+1 -> 2 | G6: =F6+1 -> 3 | H6: =G6+1 -> 4 | I6: =H6+1 -> 5 | J6: =I6+1 -> 6 | K6: =J6+1 -> 7 | L6: =K6+1 -> 8 | ... S6: =R6+1 -> 15
A8: =MAX($A$2:A3)+0.01 -> 3.01 | B8: Profit & Loss Account
B10: Production | C10: [GWh] | D10: =Calcs!D17 -> 125 | E10: =Calcs!E17 -> 125 | F10: =Calcs!F17 -> 125 | G10: =Calcs!G17 -> 125 | H10: =Calcs!H17 -> 125 | I10: =Calcs!I17 -> 125 | J10: =Calcs!J17 -> 125 | K10: =Calcs!K17 -> 125 | ... S10: =Calcs!S17 -> 125 | U10: 2012 revenue and EBITDA are shown for reference only - the vendor retains the economic benefit of the asset until 31-Dec-2012.
B12: Revenue from Electricity | C12: [£'000] | D12: =Calcs!D52 -> 6875 | E12: =Calcs!E52 -> 7011.8159 | F12: =Calcs!F52 -> 7115.9518 | G12: =Calcs!G52 -> 7186.0597 | H12: =Calcs!H52 -> 7186.0597 | I12: =Calcs!I52 -> 7151.0058 | J12: =Calcs!J52 -> 7081.5785 | K12: =Calcs!K52 -> 6978.9469 | ... S12: =Calcs!S52 -> 5230.6079
B13: Revenue from Subsidies | C13: [£'000] | D13: =Calcs!D53 -> 5000 | E13: =Calcs!E53 -> 5050 | F13: =Calcs!F53 -> 5100.5 | G13: =Calcs!G53 -> 5151.505 | H13: =Calcs!H53 -> 5177.2625 | I13: =Calcs!I53 -> 5203.1488 | J13: =Calcs!J53 -> 5229.1646 | K13: =Calcs!K53 -> 5255.3104 | ... S13: =Calcs!S53 -> 0
B14: Total Revenue | C14: [£'000] | D14: =SUM(D12:D13) -> 11875 | E14: =SUM(E12:E13) -> 12061.816 | F14: =SUM(F12:F13) -> 12216.452 | G14: =SUM(G12:G13) -> 12337.565 | H14: =SUM(H12:H13) -> 12363.322 | I14: =SUM(I12:I13) -> 12354.155 | J14: =SUM(J12:J13) -> 12310.743 | K14: =SUM(K12:K13) -> 12234.257 | ... S14: =SUM(S12:S13) -> 5230.6079
B16: Variable Costs | C16: [£'000] | D16: =-Calcs!D61 -> -625 | E16: =-Calcs!E61 -> -642.1875 | F16: =-Calcs!F61 -> -659.84766 | G16: =-Calcs!G61 -> -677.99347 | H16: =-Calcs!H61 -> -693.24832 | I16: =-Calcs!I61 -> -708.84641 | J16: =-Calcs!J61 -> -724.79545 | K16: =-Calcs!K61 -> -741.10335 | ... S16: =-Calcs!S61 -> -885.49336
B17: Fixed Costs | C17: [£'000] | D17: =-Calcs!D60 -> -2500 | E17: =-Calcs!E60 -> -2568.75 | F17: =-Calcs!F60 -> -2639.3906 | G17: =-Calcs!G60 -> -2711.9739 | H17: =-Calcs!H60 -> -2772.9933 | I17: =-Calcs!I60 -> -2835.3856 | J17: =-Calcs!J60 -> -2899.1818 | K17: =-Calcs!K60 -> -2964.4134 | ... S17: =-Calcs!S60 -> -3541.9734
B18: Total Costs | C18: [£'000] | D18: =SUM(D16:D17) -> -3125 | E18: =SUM(E16:E17) -> -3210.9375 | F18: =SUM(F16:F17) -> -3299.2383 | G18: =SUM(G16:G17) -> -3389.9673 | H18: =SUM(H16:H17) -> -3466.2416 | I18: =SUM(I16:I17) -> -3544.232 | J18: =SUM(J16:J17) -> -3623.9773 | K18: =SUM(K16:K17) -> -3705.5167 | ... S18: =SUM(S16:S17) -> -4427.4668
B20: EBITDA | C20: [£'000] | D20: =SUM(D14,D18) -> 8750 | E20: =SUM(E14,E18) -> 8850.8784 | F20: =SUM(F14,F18) -> 8917.2135 | G20: =SUM(G14,G18) -> 8947.5974 | H20: =SUM(H14,H18) -> 8897.0806 | I20: =SUM(I14,I18) -> 8809.9226 | J20: =SUM(J14,J18) -> 8686.7658 | K20: =SUM(K14,K18) -> 8528.7406 | ... S20: =SUM(S14,S18) -> 803.14112
B21: Margin | C21: [%] | D21: =IF(D14=0,0,D20/D14) -> 0.73684211 | E21: =IF(E14=0,0,E20/E14) -> 0.73379319 | F21: =IF(F14=0,0,F20/F14) -> 0.72993482 | G21: =IF(G14=0,0,G20/G14) -> 0.72523205 | H21: =IF(H14=0,0,H20/H14) -> 0.7196351 | I21: =IF(I14=0,0,I20/I14) -> 0.71311416 | J21: =IF(J14=0,0,J20/J14) -> 0.70562482 | K21: =IF(K14=0,0,K20/K14) -> 0.6971196 | ... S21: =IF(S14=0,0,S20/S14) -> 0.15354642
B23: Depreciation | C23: [£'000] | E23: =-Calcs!E67 -> -4500 | F23: =-Calcs!F67 -> -4500 | G23: =-Calcs!G67 -> -4500 | H23: =-Calcs!H67 -> -4500 | I23: =-Calcs!I67 -> -4500 | J23: =-Calcs!J67 -> -4500 | K23: =-Calcs!K67 -> -4500 | L23: =-Calcs!L67 -> -4500 | ... S23: =-Calcs!S67 -> -4500
B24: EBIT | C24: [£'000] | E24: =E20+E23 -> 4350.8784 | F24: =F20+F23 -> 4417.2135 | G24: =G20+G23 -> 4447.5974 | H24: =H20+H23 -> 4397.0806 | I24: =I20+I23 -> 4309.9226 | J24: =J20+J23 -> 4186.7658 | K24: =K20+K23 -> 4028.7406 | L24: =L20+L23 -> 4375.9078 | ... S24: =S20+S23 -> -3696.8589
B26: Interest & Financing Costs | C26: [£'000] | E26: =-Calcs!E131 -> -2064.9084 | F26: =-Calcs!F131 -> -1935.776 | G26: =-Calcs!G131 -> -1893.4483 | H26: =-Calcs!H131 -> -1848.3257 | I26: =-Calcs!I131 -> -1761.5959 | J26: =-Calcs!J131 -> -1598.613 | K26: =-Calcs!K131 -> -1379.3092 | L26: =-Calcs!L131 -> -1142.0819 | ... S26: =-Calcs!S131 -> 0
B27: Profit Before Tax | C27: [£'000] | E27: =E24+E26 -> 2285.97 | F27: =F24+F26 -> 2481.4375 | G27: =G24+G26 -> 2554.1491 | H27: =H24+H26 -> 2548.7549 | I27: =I24+I26 -> 2548.3266 | J27: =J24+J26 -> 2588.1528 | K27: =K24+K26 -> 2649.4314 | L27: =L24+L26 -> 3233.8259 | ... S27: =S24+S26 -> -3696.8589
B28: Tax | C28: [£'000] | E28: =-Calcs!E145 -> -571.4925 | F28: =-Calcs!F145 -> -620.35938 | G28: =-Calcs!G145 -> -638.53727 | H28: =-Calcs!H145 -> -637.18873 | I28: =-Calcs!I145 -> -637.08166 | J28: =-Calcs!J145 -> -647.0382 | K28: =-Calcs!K145 -> -662.35786 | L28: =-Calcs!L145 -> -808.45647 | ... S28: =-Calcs!S145 -> 0
B29: Net Income | C29: [£'000] | E29: =E27+E28 -> 1714.4775 | F29: =F27+F28 -> 1861.0781 | G29: =G27+G28 -> 1915.6118 | H29: =H27+H28 -> 1911.5662 | I29: =I27+I28 -> 1911.245 | J29: =J27+J28 -> 1941.1146 | K29: =K27+K28 -> 1987.0736 | L29: =L27+L28 -> 2425.3694 | ... S29: =S27+S28 -> -3696.8589
A33: =MAX($A$2:A32)+0.01 -> 3.02 | B33: Cashflow
B35: EBITDA | C35: [£'000] | E35: =E20 -> 8850.8784 | F35: =F20 -> 8917.2135 | G35: =G20 -> 8947.5974 | H35: =H20 -> 8897.0806 | I35: =I20 -> 8809.9226 | J35: =J20 -> 8686.7658 | K35: =K20 -> 8528.7406 | L35: =L20 -> 8875.9078 | ... S35: =S20 -> 803.14112
B36: Working Capital | C36: [£'000] | E36: =Calcs!E79 -> -10.62824 | F36: =Calcs!F79 -> -7.1494876 | G36: =Calcs!G79 -> -3.5287882 | H36: =Calcs!H79 -> 4.7194638 | I36: =Calcs!I79 -> 8.4134957 | J36: =Calcs!J79 -> 12.042387 | K36: =Calcs!K79 -> 15.556877 | L36: =Calcs!L79 -> -35.503414 | ... S36: =Calcs!S79 -> 37.854034
B37: Tax Paid | C37: [£'000] | E37: =-Calcs!E145 -> -571.4925 | F37: =-Calcs!F145 -> -620.35938 | G37: =-Calcs!G145 -> -638.53727 | H37: =-Calcs!H145 -> -637.18873 | I37: =-Calcs!I145 -> -637.08166 | J37: =-Calcs!J145 -> -647.0382 | K37: =-Calcs!K145 -> -662.35786 | L37: =-Calcs!L145 -> -808.45647 | ... S37: =-Calcs!S145 -> 0
B38: CFADS | C38: [£'000] | E38: =SUM(E35:E37) -> 8268.7577 | F38: =SUM(F35:F37) -> 8289.7047 | G38: =SUM(G35:G37) -> 8305.5313 | H38: =SUM(H35:H37) -> 8264.6114 | I38: =SUM(I35:I37) -> 8181.2544 | J38: =SUM(J35:J37) -> 8051.77 | K38: =SUM(K35:K37) -> 7881.9396 | L38: =SUM(L35:L37) -> 8031.9479 | ... S38: =SUM(S35:S37) -> 840.99515
B40: Senior Interest | C40: [£'000] | E40: =-Calcs!E103 -> -1979.5043 | F40: =-Calcs!F103 -> -1850.3719 | G40: =-Calcs!G103 -> -1808.0442 | H40: =-Calcs!H103 -> -1762.9216 | I40: =-Calcs!I103 -> -1676.1918 | J40: =-Calcs!J103 -> -1513.2089 | K40: =-Calcs!K103 -> -1293.905 | L40: =-Calcs!L103 -> -1056.6778 | ... S40: =-Calcs!S103 -> 0
B41: Senior Principal Repayment | C41: [£'000] | E41: =-Calcs!E105 -> -4381.0785 | F41: =-Calcs!F105 -> -4526.324 | G41: =-Calcs!G105 -> -4580.8261 | H41: =-Calcs!H105 -> -4594.4718 | I41: =-Calcs!I105 -> -4617.0808 | J41: =-Calcs!J105 -> -4680.4603 | K41: =-Calcs!K105 -> -4769.1254 | L41: =-Calcs!L105 -> -5121.7437 | ... S41: =-Calcs!S105 -> 0
B42: Total Senior Debt Service | C42: [£'000] | E42: =SUM(E40:E41) -> -6360.5828 | F42: =SUM(F40:F41) -> -6376.6959 | G42: =SUM(G40:G41) -> -6388.8702 | H42: =SUM(H40:H41) -> -6357.3934 | I42: =SUM(I40:I41) -> -6293.2726 | J42: =SUM(J40:J41) -> -6193.6693 | K42: =SUM(K40:K41) -> -6063.0305 | L42: =SUM(L40:L41) -> -6178.4214 | ... S42: =SUM(S40:S41) -> 0
B43: DSCR | C43: [x] | E43: =IF(E42=0,"n/a",-E38/E42) -> 1.3 | F43: =IF(F42=0,"n/a",-F38/F42) -> 1.3 | G43: =IF(G42=0,"n/a",-G38/G42) -> 1.3 | H43: =IF(H42=0,"n/a",-H38/H42) -> 1.3 | I43: =IF(I42=0,"n/a",-I38/I42) -> 1.3 | J43: =IF(J42=0,"n/a",-J38/J42) -> 1.3 | K43: =IF(K42=0,"n/a",-K38/K42) -> 1.3 | L43: =IF(L42=0,"n/a",-L38/L42) -> 1.3 | ... S43: =IF(S42=0,"n/a",-S38/S42) -> n/a
B45: Release of Opening Cash Balance | C45: [£'000] | E45: =$D$74 -> 3500 | F45: 0 | G45: 0 | H45: 0 | I45: 0 | J45: 0 | K45: 0 | L45: 0 | M45: 0 | N45: 0 | O45: 0 | P45: 0 | Q45: 0 | R45: 0 | S45: 0
B46: Net Cashflows to Equity | C46: [£'000] | E46: =E38+E42+E45 -> 5408.1748 | F46: =F38+F42+F45 -> 1913.0088 | G46: =G38+G42+G45 -> 1916.6611 | H46: =H38+H42+H45 -> 1907.218 | I46: =I38+I42+I45 -> 1887.9818 | J46: =J38+J42+J45 -> 1858.1008 | K46: =K38+K42+K45 -> 1818.9091 | L46: =L38+L42+L45 -> 1853.5264 | ... S46: =S38+S42+S45 -> 840.99515
B47: Equity Cash Flow (incl. day-one investment) | C47: [£'000] | D47: =-D56 -> -14799.873 | E47: =E46 -> 5408.1748 | F47: =F46 -> 1913.0088 | G47: =G46 -> 1916.6611 | H47: =H46 -> 1907.218 | I47: =I46 -> 1887.9818 | J47: =J46 -> 1858.1008 | K47: =K46 -> 1818.9091 | L47: =L46 -> 1853.5264 | ... S47: =S46 -> 840.99515
A49: =MAX($A$2:A47)+0.01 -> 3.03 | B49: Valuation
B51: Buy and Hold
B52: Equity Purchase Price payable to Vendor | C52: [£'000] | D52: =NPV(Assumptions!$D$93,E46:S46)+Calcs!$D$98-Calcs!$D$99-Assumptions!$D$92 -> 64517.503
B53: Transaction Costs | C53: [£'000] | D53: =Assumptions!$D$92 -> 500
B54: Upfront Debt Fee | C54: [£'000] | D54: =Calcs!$D$99 -> 1024.8496
B55: Less: Senior Debt Drawn | C55: [£'000] | D55: =-Calcs!$D$98 -> -51242.479
B56: Investor Equity Investment | C56: [£'000] | D56: =SUM(D52:D55) -> 14799.873
B57: IRR | C57: [%] | D57: =IRR(D47:S47) -> 0.12
B58: Money Multiple | C58: [x] | D58: =SUM(E47:S47)/-D47 -> 1.8149235
B59: Implied Enterprise Value (price less cash acquired) | C59: [£'000] | D59: =D52-D74 -> 61017.503
B60: Exit Analysis
B62: Exit Year | C62: [year] | D62: =Assumptions!$D$95 -> 2014
B63: Buyer's Required IRR (levered) | C63: [%] | D63: =Assumptions!$D$96 -> 0.11
B64: Equity Value to Buyer at Exit | C64: [£'000] | D64: =NPV(D63,G46:S46) -> 11062.028
B65: Senior Debt Outstanding at Exit | C65: [£'000] | D65: =Calcs!F106 -> 42335.076
B66: Enterprise Value at Exit | C66: [£'000] | D66: =D64+D65 -> 53397.105
B67: Exit Fee (0.25% of EV) | C67: [£'000] | D67: =-Assumptions!$D$97*D66 -> -133.49276
B68: Net Equity Proceeds to Investor | C68: [£'000] | D68: =D64+D67 -> 10928.536
B69: Investor IRR on a 2-Year Hold | C69: [%] | D69: =Analysis!$D$90 -> 0.13195321
A70: =MAX($A$2:A67)+0.01 -> 3.04 | B70: Simplified Balance Sheet
B72: Assets
B74: Cash | C74: [£'000] | D74: 3500 | E74: =D74+E38+E42-E46 -> 0 | F74: =E74+F38+F42-F46 -> 0 | G74: =F74+G38+G42-G46 -> 0 | H74: =G74+H38+H42-H46 -> 0 | I74: =H74+I38+I42-I46 -> 0 | J74: =I74+J38+J42-J46 -> 0 | K74: =J74+K38+K42-K46 -> 0 | L74: =K74+L38+L42-L46 -> 0 | ... S74: =R74+S38+S42-S46 -> 0 | U74: Column D is the vendor balance sheet as provided (pre-acquisition). Columns E onwards reflect the post-acquisition capital structure - see the Sources & Uses block below.
B75: Receivables | C75: [£'000] | D75: 1200 | E75: =Calcs!E76 -> 1218.8782 | F75: =Calcs!F76 -> 1234.5046 | G75: =Calcs!G76 -> 1246.7434 | H75: =Calcs!H76 -> 1249.3462 | I75: =Calcs!I76 -> 1248.4198 | J75: =Calcs!J76 -> 1244.033 | K75: =Calcs!K76 -> 1236.3039 | L75: =Calcs!L76 -> 1279.8112 | ... S75: =Calcs!S76 -> 528.56669
B76: PP&E | C76: [£'000] | D76: 67500 | E76: =D76+E23 -> 63000 | F76: =E76+F23 -> 58500 | G76: =F76+G23 -> 54000 | H76: =G76+H23 -> 49500 | I76: =H76+I23 -> 45000 | J76: =I76+J23 -> 40500 | K76: =J76+K23 -> 36000 | L76: =K76+L23 -> 31500 | ... S76: =R76+S23 -> 0
B77: Total Assets | C77: [£'000] | D77: =SUM(D74:D76) -> 72200 | E77: =SUM(E74:E76) -> 64218.878 | F77: =SUM(F74:F76) -> 59734.505 | G77: =SUM(G74:G76) -> 55246.743 | H77: =SUM(H74:H76) -> 50749.346 | I77: =SUM(I74:I76) -> 46248.42 | J77: =SUM(J74:J76) -> 41744.033 | K77: =SUM(K74:K76) -> 37236.304 | ... S77: =SUM(S74:S76) -> 528.56669
B79: Liabilities
B81: Payables | C81: [£'000] | D81: 300 | E81: =Calcs!E77 -> 308.25 | F81: =Calcs!F77 -> 316.72688 | G81: =Calcs!G77 -> 325.43686 | H81: =Calcs!H77 -> 332.75919 | I81: =Calcs!I77 -> 340.24628 | J81: =Calcs!J77 -> 347.90182 | K81: =Calcs!K77 -> 355.72961 | L81: =Calcs!L77 -> 363.73352 | ... S81: =Calcs!S77 -> 425.03681
B82: Senior Debt (net of unamortised fee) | C82: [£'000] | D82: 0 | E82: =Calcs!E106-(Calcs!$D$99-SUM(Calcs!$E$107:E107)) -> 45921.955 | F82: =Calcs!F106-(Calcs!$D$99-SUM(Calcs!$E$107:F107)) -> 41481.035 | G82: =Calcs!G106-(Calcs!$D$99-SUM(Calcs!$E$107:G107)) -> 36985.613 | H82: =Calcs!H106-(Calcs!$D$99-SUM(Calcs!$E$107:H107)) -> 32476.545 | I82: =Calcs!I106-(Calcs!$D$99-SUM(Calcs!$E$107:I107)) -> 27944.869 | J82: =Calcs!J106-(Calcs!$D$99-SUM(Calcs!$E$107:J107)) -> 23349.812 | K82: =Calcs!K106-(Calcs!$D$99-SUM(Calcs!$E$107:K107)) -> 18666.091 | L82: =Calcs!L106-(Calcs!$D$99-SUM(Calcs!$E$107:L107)) -> 13629.752 | ... S82: =Calcs!S106-(Calcs!$D$99-SUM(Calcs!$E$107:S107)) -> 0
B83: Equity & Retained Earnings | C83: [£'000] | D83: 71900 | E83: =$D$100+E29-E46 -> 17988.673 | F83: =E83+F29-F46 -> 17936.743 | G83: =F83+G29-G46 -> 17935.694 | H83: =G83+H29-H46 -> 17940.042 | I83: =H83+I29-I46 -> 17963.305 | J83: =I83+J29-J46 -> 18046.319 | K83: =J83+K29-K46 -> 18214.483 | L83: =K83+L29-L46 -> 18786.326 | M83: =L83+M29-M46 -> 19715.928 | ... S83: =R83+S29-S46 -> 103.52988
B84: Total Liabilities & Equity | C84: [£'000] | D84: =SUM(D81:D83) -> 72200 | E84: =SUM(E81:E83) -> 64218.878 | F84: =SUM(F81:F83) -> 59734.505 | G84: =SUM(G81:G83) -> 55246.743 | H84: =SUM(H81:H83) -> 50749.346 | I84: =SUM(I81:I83) -> 46248.42 | J84: =SUM(J81:J83) -> 41744.033 | K84: =SUM(K81:K83) -> 37236.304 | ... S84: =SUM(S81:S83) -> 528.56669
B86: Balance Check | C86: [£'000] | D86: =D77-D84 -> 0 | E86: =E77-E84 -> 0 | F86: =F77-F84 -> 0 | G86: =G77-G84 -> 0 | H86: =H77-H84 -> 0 | I86: =I77-I84 -> 0 | J86: =J77-J84 -> 0 | K86: =K77-K84 -> 0 | ... S86: =S77-S84 -> -3.4106051e-12
A88: =MAX($A$2:A87)+0.01 -> 3.05 | B88: Sources & Uses at Close
B90: Sources
B91: Senior Debt Drawn | C91: [£'000] | D91: =Calcs!$D$98 -> 51242.479
B92: Investor Equity | C92: [£'000] | D92: =D56 -> 14799.873
B93: Total Sources | C93: [£'000] | D93: =SUM(D91:D92) -> 66042.352
B95: Uses
B96: Equity Purchase Price | C96: [£'000] | D96: =D52 -> 64517.503
B97: Transaction Costs | C97: [£'000] | D97: =D53 -> 500
B98: Upfront Debt Fee | C98: [£'000] | D98: =D54 -> 1024.8496
B99: Total Uses | C99: [£'000] | D99: =SUM(D96:D98) -> 66042.352
B100: Post-Acquisition Opening Equity (debt pushed down) | C100: [£'000] | D100: =D83-(Calcs!$D$98-Calcs!$D$99) -> 21682.371
B101: Check: Sources less Uses (must be nil) | C101: [£'000] | D101: =D93-D99 -> 0

Sheet Analysis
A2: =Output!A2+1 -> 4 | B2: Project Storm - Key Results and Supporting Analysis
B4: Period End | D4: =Output!D4 -> 41274 | E4: =Output!E4 -> 41639 | F4: =Output!F4 -> 42004 | G4: =Output!G4 -> 42369 | H4: =Output!H4 -> 42735 | I4: =Output!I4 -> 43100 | J4: =Output!J4 -> 43465 | K4: =Output!K4 -> 43830 | ... S4: =Output!S4 -> 46752
B5: Calendar Year | D5: =YEAR(D4) -> 2012 | E5: =YEAR(E4) -> 2013 | F5: =YEAR(F4) -> 2014 | G5: =YEAR(G4) -> 2015 | H5: =YEAR(H4) -> 2016 | I5: =YEAR(I4) -> 2017 | J5: =YEAR(J4) -> 2018 | K5: =YEAR(K4) -> 2019 | ... S5: =YEAR(S4) -> 2027
B6: Model Year | D6: 0 | E6: =D6+1 -> 1 | F6: =E6+1 -> 2 | G6: =F6+1 -> 3 | H6: =G6+1 -> 4 | I6: =H6+1 -> 5 | J6: =I6+1 -> 6 | K6: =J6+1 -> 7 | L6: =K6+1 -> 8 | ... S6: =R6+1 -> 15
A8: =MAX($A$2:A7)+0.01 -> 4.01 | B8: Summary of Results
B10: Recommended bid price - equity value to vendor | C10: [£'000] | D10: =Output!$D$52 -> 64517.503
B11: Implied enterprise value | C11: [£'000] | D11: =Output!$D$59 -> 61017.503
B12: Enterprise value per MW | C12: [£'000/MW] | D12: =D11/Assumptions!$D$47 -> 1220.3501
B13: Senior debt sized | C13: [£'000] | D13: =Calcs!$D$98 -> 51242.479
B14: Investor equity cheque | C14: [£'000] | D14: =Output!$D$56 -> 14799.873
B15: Buy & hold equity IRR | C15: [%] | D15: =Output!$D$57 -> 0.12
B17: Downside: equity IRR - P90 for 10 years, then P75 | C17: [%] | D17: =$D$75 -> 0.068863578
B18: Minimum DSCR in that scenario | C18: [x] | D18: =$D$76 -> 1.2102096
B20: Exit: investor IRR on a 2-year hold, exit priced at 11% | C20: [%] | D20: =$D$90 -> 0.13195321
B21: Net equity proceeds at exit | C21: [£'000] | D21: =Output!$D$68 -> 10928.536
B23: Hedging: 12-year amortising swap rate | C23: [%] | D23: =$D$103 -> 0.016381739
B24: All-in fixed cost of debt (swap + margin) | C24: [%] | D24: =$D$104 -> 0.046381739
B26: Tax: impact of the 30% interest cap on the bid price | C26: [£'000] | D26: =$D$120 -> 0
B27: Minimum headroom under the cap | C27: [£'000] | D27: =$D$116 -> 388.26254
B29: Sub-debt: subordinated loan sized | C29: [£'000] | D29: =$D$131 -> 6226.7708
B30: Investor equity IRR with subordinated loan | C30: [%] | D30: =$D$168 -> 0.13948891
B31: Uplift versus the base case | C31: [bps] | D31: =($D$168-Output!$D$57)*10000 -> 194.88907
B33: The PPA analysis is on the "Sensitivities" sheet and discussed in the valuation memo.
A35: =MAX($A$2:A34)+0.01 -> 4.02 | B35: Downside case - P90 for the first 10 years, P75 thereafter
B37: Production | C37: [GWh] | D37: =Calcs!D15 -> 125 | E37: =IF(E$5<=$D$5+10,Calcs!E16,Calcs!E15) -> 117.5 | F37: =IF(F$5<=$D$5+10,Calcs!F16,Calcs!F15) -> 117.5 | G37: =IF(G$5<=$D$5+10,Calcs!G16,Calcs!G15) -> 117.5 | H37: =IF(H$5<=$D$5+10,Calcs!H16,Calcs!H15) -> 117.5 | I37: =IF(I$5<=$D$5+10,Calcs!I16,Calcs!I15) -> 117.5 | J37: =IF(J$5<=$D$5+10,Calcs!J16,Calcs!J15) -> 117.5 | K37: =IF(K$5<=$D$5+10,Calcs!K16,Calcs!K15) -> 117.5 | L37: =IF(L$5<=$D$5+10,Calcs!L16,Calcs!L15) -> 117.5 | ... S37: =IF(S$5<=$D$5+10,Calcs!S16,Calcs!S15) -> 125
B39: Revenue from Electricity | C39: [£'000] | D39: =D37*Calcs!D49 -> 6875 | E39: =E37*Calcs!E49 -> 6591.107 | F39: =F37*Calcs!F49 -> 6688.9947 | G39: =G37*Calcs!G49 -> 6754.8961 | H39: =H37*Calcs!H49 -> 6754.8961 | I39: =I37*Calcs!I49 -> 6721.9454 | J39: =J37*Calcs!J49 -> 6656.6838 | K39: =K37*Calcs!K49 -> 6560.2101 | ... S39: =S37*Calcs!S49 -> 5230.6079
B40: Revenue from Subsidy | C40: [£'000] | D40: =D37*Calcs!D50 -> 5000 | E40: =E37*Calcs!E50 -> 4747 | F40: =F37*Calcs!F50 -> 4794.47 | G40: =G37*Calcs!G50 -> 4842.4147 | H40: =H37*Calcs!H50 -> 4866.6268 | I40: =I37*Calcs!I50 -> 4890.9599 | J40: =J37*Calcs!J50 -> 4915.4147 | K40: =K37*Calcs!K50 -> 4939.9918 | ... S40: =S37*Calcs!S50 -> 0
B41: Total Revenue | C41: [£'000] | D41: =SUM(D39:D40) -> 11875 | E41: =SUM(E39:E40) -> 11338.107 | F41: =SUM(F39:F40) -> 11483.465 | G41: =SUM(G39:G40) -> 11597.311 | H41: =SUM(H39:H40) -> 11621.523 | I41: =SUM(I39:I40) -> 11612.905 | J41: =SUM(J39:J40) -> 11572.099 | K41: =SUM(K39:K40) -> 11500.202 | ... S41: =SUM(S39:S40) -> 5230.6079
B42: Fixed Costs | C42: [£'000] | D42: =Calcs!D60 -> 2500 | E42: =Calcs!E60 -> 2568.75 | F42: =Calcs!F60 -> 2639.3906 | G42: =Calcs!G60 -> 2711.9739 | H42: =Calcs!H60 -> 2772.9933 | I42: =Calcs!I60 -> 2835.3856 | J42: =Calcs!J60 -> 2899.1818 | K42: =Calcs!K60 -> 2964.4134 | ... S42: =Calcs!S60 -> 3541.9734
B43: Variable Costs | C43: [£'000] | D43: =Assumptions!$D$63*D37*Calcs!D9 -> 625 | E43: =Assumptions!$D$63*E37*Calcs!E9 -> 603.65625 | F43: =Assumptions!$D$63*F37*Calcs!F9 -> 620.2568 | G43: =Assumptions!$D$63*G37*Calcs!G9 -> 637.31386 | H43: =Assumptions!$D$63*H37*Calcs!H9 -> 651.65342 | I43: =Assumptions!$D$63*I37*Calcs!I9 -> 666.31562 | J43: =Assumptions!$D$63*J37*Calcs!J9 -> 681.30772 | K43: =Assumptions!$D$63*K37*Calcs!K9 -> 696.63715 | ... S43: =Assumptions!$D$63*S37*Calcs!S9 -> 885.49336
B44: Total Operating Costs | C44: [£'000] | D44: =SUM(D42:D43) -> 3125 | E44: =SUM(E42:E43) -> 3172.4062 | F44: =SUM(F42:F43) -> 3259.6474 | G44: =SUM(G42:G43) -> 3349.2877 | H44: =SUM(H42:H43) -> 3424.6467 | I44: =SUM(I42:I43) -> 3501.7013 | J44: =SUM(J42:J43) -> 3580.4895 | K44: =SUM(K42:K43) -> 3661.0505 | ... S44: =SUM(S42:S43) -> 4427.4668
B46: EBITDA | C46: [£'000] | D46: =D41-D44 -> 8750 | E46: =E41-E44 -> 8165.7007 | F46: =F41-F44 -> 8223.8173 | G46: =G41-G44 -> 8248.0231 | H46: =H41-H44 -> 8196.8762 | I46: =I41-I44 -> 8111.2041 | J46: =J41-J44 -> 7991.609 | K46: =K41-K44 -> 7839.1514 | ... S46: =S41-S44 -> 803.14112
B47: Depreciation | C47: [£'000] | E47: =Calcs!E67 -> 4500 | F47: =Calcs!F67 -> 4500 | G47: =Calcs!G67 -> 4500 | H47: =Calcs!H67 -> 4500 | I47: =Calcs!I67 -> 4500 | J47: =Calcs!J67 -> 4500 | K47: =Calcs!K67 -> 4500 | L47: =Calcs!L67 -> 4500 | ... S47: =Calcs!S67 -> 4500
B49: Financing Costs (senior debt already committed) | C49: [£'000] | E49: =Calcs!E131 -> 2064.9084 | F49: =Calcs!F131 -> 1935.776 | G49: =Calcs!G131 -> 1893.4483 | H49: =Calcs!H131 -> 1848.3257 | I49: =Calcs!I131 -> 1761.5959 | J49: =Calcs!J131 -> 1598.613 | K49: =Calcs!K131 -> 1379.3092 | L49: =Calcs!L131 -> 1142.0819 | ... S49: =Calcs!S131 -> 0
B50: Interest Cap (30% of EBITDA) | C50: [£'000] | E50: =Assumptions!$D$70*MAX(E46,0) -> 2449.7102 | F50: =Assumptions!$D$70*MAX(F46,0) -> 2467.1452 | G50: =Assumptions!$D$70*MAX(G46,0) -> 2474.4069 | H50: =Assumptions!$D$70*MAX(H46,0) -> 2459.0629 | I50: =Assumptions!$D$70*MAX(I46,0) -> 2433.3612 | J50: =Assumptions!$D$70*MAX(J46,0) -> 2397.4827 | K50: =Assumptions!$D$70*MAX(K46,0) -> 2351.7454 | L50: =Assumptions!$D$70*MAX(L46,0) -> 2448.446 | ... S50: =Assumptions!$D$70*MAX(S46,0) -> 240.94233
B51: Disallowed Interest b/f | C51: [£'000] | E51: =D54 -> 0 | F51: =E54 -> 0 | G51: =F54 -> 0 | H51: =G54 -> 0 | I51: =H54 -> 0 | J51: =I54 -> 0 | K51: =J54 -> 0 | L51: =K54 -> 0 | ... S51: =R54 -> 0
B52: Allowed - Current Year | C52: [£'000] | E52: =MIN(E49,E50) -> 2064.9084 | F52: =MIN(F49,F50) -> 1935.776 | G52: =MIN(G49,G50) -> 1893.4483 | H52: =MIN(H49,H50) -> 1848.3257 | I52: =MIN(I49,I50) -> 1761.5959 | J52: =MIN(J49,J50) -> 1598.613 | K52: =MIN(K49,K50) -> 1379.3092 | L52: =MIN(L49,L50) -> 1142.0819 | ... S52: =MIN(S49,S50) -> 0
B53: Utilisation of b/f Disallowed Interest | C53: [£'000] | E53: =MIN(E51,MAX(E50-E49,0)) -> 0 | F53: =MIN(F51,MAX(F50-F49,0)) -> 0 | G53: =MIN(G51,MAX(G50-G49,0)) -> 0 | H53: =MIN(H51,MAX(H50-H49,0)) -> 0 | I53: =MIN(I51,MAX(I50-I49,0)) -> 0 | J53: =MIN(J51,MAX(J50-J49,0)) -> 0 | K53: =MIN(K51,MAX(K50-K49,0)) -> 0 | L53: =MIN(L51,MAX(L50-L49,0)) -> 0 | ... S53: =MIN(S51,MAX(S50-S49,0)) -> 0
B54: Disallowed Interest c/f | C54: [£'000] | D54: 0 | E54: =E51+MAX(E49-E50,0)-E53 -> 0 | F54: =F51+MAX(F49-F50,0)-F53 -> 0 | G54: =G51+MAX(G49-G50,0)-G53 -> 0 | H54: =H51+MAX(H49-H50,0)-H53 -> 0 | I54: =I51+MAX(I49-I50,0)-I53 -> 0 | J54: =J51+MAX(J49-J50,0)-J53 -> 0 | K54: =K51+MAX(K49-K50,0)-K53 -> 0 | L54: =L51+MAX(L49-L50,0)-L53 -> 0 | ... S54: =S51+MAX(S49-S50,0)-S53 -> 0
B55: Total Interest Allowed | C55: [£'000] | E55: =E52+E53 -> 2064.9084 | F55: =F52+F53 -> 1935.776 | G55: =G52+G53 -> 1893.4483 | H55: =H52+H53 -> 1848.3257 | I55: =I52+I53 -> 1761.5959 | J55: =J52+J53 -> 1598.613 | K55: =K52+K53 -> 1379.3092 | L55: =L52+L53 -> 1142.0819 | ... S55: =S52+S53 -> 0
B57: Profit Before Tax | C57: [£'000] | E57: =E46-E47-E55 -> 1600.7923 | F57: =F46-F47-F55 -> 1788.0413 | G57: =G46-G47-G55 -> 1854.5748 | H57: =H46-H47-H55 -> 1848.5505 | I57: =I46-I47-I55 -> 1849.6082 | J57: =J46-J47-J55 -> 1892.9959 | K57: =K46-K47-K55 -> 1959.8422 | L57: =L46-L47-L55 -> 2519.4046 | ... S57: =S46-S47-S55 -> -3696.8589
B58: Tax Losses b/f | C58: [£'000] | E58: =D60 -> 0 | F58: =E60 -> 0 | G58: =F60 -> 0 | H58: =G60 -> 0 | I58: =H60 -> 0 | J58: =I60 -> 0 | K58: =J60 -> 0 | L58: =K60 -> 0 | ... S58: =R60 -> 11593.83
B59: Taxable Profit | C59: [£'000] | E59: =MAX(E57-E58,0) -> 1600.7923 | F59: =MAX(F57-F58,0) -> 1788.0413 | G59: =MAX(G57-G58,0) -> 1854.5748 | H59: =MAX(H57-H58,0) -> 1848.5505 | I59: =MAX(I57-I58,0) -> 1849.6082 | J59: =MAX(J57-J58,0) -> 1892.9959 | K59: =MAX(K57-K58,0) -> 1959.8422 | L59: =MAX(L57-L58,0) -> 2519.4046 | ... S59: =MAX(S57-S58,0) -> 0
B60: Tax Losses c/f | C60: [£'000] | D60: 0 | E60: =MAX(E58-E57,0) -> 0 | F60: =MAX(F58-F57,0) -> 0 | G60: =MAX(G58-G57,0) -> 0 | H60: =MAX(H58-H57,0) -> 0 | I60: =MAX(I58-I57,0) -> 0 | J60: =MAX(J58-J57,0) -> 0 | K60: =MAX(K58-K57,0) -> 0 | L60: =MAX(L58-L57,0) -> 0 | ... S60: =MAX(S58-S57,0) -> 15290.689
B61: Tax Charge | C61: [£'000] | E61: =E59*Assumptions!$D$69 -> 400.19807 | F61: =F59*Assumptions!$D$69 -> 447.01031 | G61: =G59*Assumptions!$D$69 -> 463.6437 | H61: =H59*Assumptions!$D$69 -> 462.13762 | I61: =I59*Assumptions!$D$69 -> 462.40204 | J61: =J59*Assumptions!$D$69 -> 473.24898 | K61: =K59*Assumptions!$D$69 -> 489.96055 | L61: =L59*Assumptions!$D$69 -> 629.85116 | ... S61: =S59*Assumptions!$D$69 -> 0
B63: Receivables | C63: [£'000] | D63: =D41*Calcs!D73/365 -> 1200 | E63: =E41*Calcs!E73/365 -> 1145.7455 | F63: =F41*Calcs!F73/365 -> 1160.4343 | G63: =G41*Calcs!G73/365 -> 1171.9388 | H63: =H41*Calcs!H73/365 -> 1174.3855 | I63: =I41*Calcs!I73/365 -> 1173.5146 | J63: =J41*Calcs!J73/365 -> 1169.391 | K63: =K41*Calcs!K73/365 -> 1162.1257 | ... S63: =S41*Calcs!S73/365 -> 528.56669
B64: Payables | C64: [£'000] | D64: =D44*Calcs!D74/365 -> 300 | E64: =E44*Calcs!E74/365 -> 304.551 | F64: =F44*Calcs!F74/365 -> 312.92615 | G64: =G44*Calcs!G74/365 -> 321.53162 | H64: =H44*Calcs!H74/365 -> 328.76608 | I64: =I44*Calcs!I74/365 -> 336.16332 | J64: =J44*Calcs!J74/365 -> 343.72699 | K64: =K44*Calcs!K74/365 -> 351.46085 | ... S64: =S44*Calcs!S74/365 -> 425.03681
B65: Net Working Capital | C65: [£'000] | D65: =D63-D64 -> 900 | E65: =E63-E64 -> 841.19455 | F65: =F63-F64 -> 847.50817 | G65: =G63-G64 -> 850.40716 | H65: =H63-H64 -> 845.61939 | I65: =I63-I64 -> 837.35132 | J65: =J63-J64 -> 825.66401 | K65: =K63-K64 -> 810.66481 | ... S65: =S63-S64 -> 103.52988
B66: Movement in Working Capital | C66: [£'000] | E66: =-(E65-D65) -> 58.805454 | F66: =-(F65-E65) -> -6.3136284 | G66: =-(G65-F65) -> -2.8989814 | H66: =-(H65-G65) -> 4.7877677 | I66: =-(I65-H65) -> 8.2680659 | J66: =-(J65-I65) -> 11.68731 | K66: =-(K65-J65) -> 14.999198 | L66: =-(L65-K65) -> -32.989021 | ... S66: =-(S65-R65) -> 37.854034
B68: CFADS | C68: [£'000] | E68: =E46-E61+E66 -> 7824.3081 | F68: =F46-F61+F66 -> 7770.4933 | G68: =G46-G61+G66 -> 7781.4804 | H68: =H46-H61+H66 -> 7739.5263 | I68: =I46-I61+I66 -> 7657.0701 | J68: =J46-J61+J66 -> 7530.0473 | K68: =K46-K61+K66 -> 7364.19 | L68: =L46-L61+L66 -> 7498.6463 | ... S68: =S46-S61+S66 -> 840.99515
B69: Senior Debt Service (unchanged) | C69: [£'000] | E69: =Calcs!E104 -> 6360.5828 | F69: =Calcs!F104 -> 6376.6959 | G69: =Calcs!G104 -> 6388.8702 | H69: =Calcs!H104 -> 6357.3934 | I69: =Calcs!I104 -> 6293.2726 | J69: =Calcs!J104 -> 6193.6693 | K69: =Calcs!K104 -> 6063.0305 | L69: =Calcs!L104 -> 6178.4214 | ... S69: =Calcs!S104 -> 0
B70: DSCR | C70: [x] | E70: =IF(E69=0,"n/a",E68/E69) -> 1.2301244 | F70: =IF(F69=0,"n/a",F68/F69) -> 1.2185767 | G70: =IF(G69=0,"n/a",G68/G69) -> 1.2179744 | H70: =IF(H69=0,"n/a",H68/H69) -> 1.2174056 | I70: =IF(I69=0,"n/a",I68/I69) -> 1.2167072 | J70: =IF(J69=0,"n/a",J68/J69) -> 1.2157652 | K70: =IF(K69=0,"n/a",K68/K69) -> 1.2146055 | L70: =IF(L69=0,"n/a",L68/L69) -> 1.2136832 | ... S70: =IF(S69=0,"n/a",S68/S69) -> n/a
B71: Release of Opening Cash Balance | C71: [£'000] | E71: =Output!$D$74 -> 3500 | F71: 0 | G71: 0 | H71: 0 | I71: 0 | J71: 0 | K71: 0 | L71: 0 | M71: 0 | N71: 0 | O71: 0 | P71: 0 | Q71: 0 | R71: 0 | S71: 0
B72: Net Cash Flow to Equity | C72: [£'000] | E72: =E68-E69+E71 -> 4963.7253 | F72: =F68-F69+F71 -> 1393.7974 | G72: =G68-G69+G71 -> 1392.6102 | H72: =H68-H69+H71 -> 1382.133 | I72: =I68-I69+I71 -> 1363.7975 | J72: =J68-J69+J71 -> 1336.3781 | K72: =K68-K69+K71 -> 1301.1595 | L72: =L68-L69+L71 -> 1320.2249 | ... S72: =S68-S69+S71 -> 840.99515
B73: Equity Cash Flow (incl. day-one investment) | C73: [£'000] | D73: =-Output!$D$56 -> -14799.873 | E73: =E72 -> 4963.7253 | F73: =F72 -> 1393.7974 | G73: =G72 -> 1392.6102 | H73: =H72 -> 1382.133 | I73: =I72 -> 1363.7975 | J73: =J72 -> 1336.3781 | K73: =K72 -> 1301.1595 | L73: =L72 -> 1320.2249 | ... S73: =S72 -> 840.99515
B75: Equity IRR | C75: [%] | D75: =IRR(D73:S73) -> 0.068863578
B76: Minimum DSCR over the debt life | C76: [x] | D76: =MIN(E70:P70) -> 1.2102096
B77: Money Multiple | C77: [x] | D77: =SUM(E73:S73)/-D73 -> 1.4616572
A80: =MAX($A$2:A79)+0.01 -> 4.03 | B80: Exit case - sale to an infrastructure fund after 2 years
B82: Buyer's Required IRR (levered, same base case) | C82: [%] | D82: =Assumptions!$D$96 -> 0.11
B83: Dividends acquired by the buyer (2015-2027) | C83: [£'000] | G83: =Output!G46 -> 1916.6611 | H83: =Output!H46 -> 1907.218 | I83: =Output!I46 -> 1887.9818 | J83: =Output!J46 -> 1858.1008 | K83: =Output!K46 -> 1818.9091 | L83: =Output!L46 -> 1853.5264 | M83: =Output!M46 -> 1881.6114 | N83: =Output!N46 -> 1682.6526 | ... S83: =Output!S46 -> 840.99515
B84: Equity Value to Buyer at 31-Dec-2014 | C84: [£'000] | D84: =Output!$D$64 -> 11062.028
B85: Senior Debt Outstanding at Exit | C85: [£'000] | D85: =Output!$D$65 -> 42335.076
B86: Enterprise Value at Exit | C86: [£'000] | D86: =D84+D85 -> 53397.105
B87: Exit Fee (0.25% of EV) | C87: [£'000] | D87: =Output!$D$67 -> -133.49276
B88: Net Equity Proceeds to Investor | C88: [£'000] | D88: =D84+D87 -> 10928.536
B89: Investor Cash Flow | C89: [£'000] | D89: =-Output!$D$56 -> -14799.873 | E89: =Output!E46 -> 5408.1748 | F89: =Output!F46+$D$88 -> 12841.544
B90: Investor IRR on a 2-Year Hold | C90: [%] | D90: =IRR(D89:F89) -> 0.13195321
B91: Money Multiple | C91: [x] | D91: =SUM(E89:F89)/-D89 -> 1.2330997
B92: Uplift versus the 12% buy & hold case | C92: [bps] | D92: =(D90-Output!$D$57)*10000 -> 119.53208
A95: =MAX($A$2:A94)+0.01 -> 4.04 | B95: Interest rate hedge - swap rate on the hedged portion of the senior debt
B97: Hedged Notional (85% of opening principal) | C97: [£'000] | E97: =Calcs!E121 -> 43556.107 | F97: =Calcs!F121 -> 39832.19 | G97: =Calcs!G121 -> 35984.815 | H97: =Calcs!H121 -> 32091.113 | I97: =Calcs!I121 -> 28185.812 | J97: =Calcs!J121 -> 24261.293 | K97: =Calcs!K121 -> 20282.902 | L97: =Calcs!L121 -> 16229.145 | ... S97: =Calcs!S121 -> 0
B98: LIBOR Forward Rate | C98: [%] | E98: =IF(E97=0,0,Assumptions!E17) -> 0.0086301431 | F98: =IF(F97=0,0,Assumptions!F17) -> 0.0094860561 | G98: =IF(G97=0,0,Assumptions!G17) -> 0.012707946 | H98: =IF(H97=0,0,Assumptions!H17) -> 0.016694652 | I98: =IF(I97=0,0,Assumptions!I17) -> 0.020548944 | J98: =IF(J97=0,0,Assumptions!J17) -> 0.023015624 | K98: =IF(K97=0,0,Assumptions!K17) -> 0.024223962 | L98: =IF(L97=0,0,Assumptions!L17) -> 0.025343402 | ... S98: =IF(S97=0,0,Assumptions!S17) -> 0
B99: Discount Factor at LIBOR | C99: [x] | E99: =Calcs!E122 -> 0.9914437 | F99: =Calcs!F122 -> 0.98212719 | G99: =Calcs!G122 -> 0.96980298 | H99: =Calcs!H122 -> 0.95387831 | I99: =Calcs!I122 -> 0.9346718 | J99: =Calcs!J122 -> 0.91364372 | K99: =Calcs!K122 -> 0.89203509 | L99: =Calcs!L122 -> 0.86998667 | ... S99: =Calcs!S122 -> 0
B100: Floating Leg (Notional x LIBOR x DF) | C100: [£'000] | E100: =Calcs!E123 -> 372.67916 | F100: =Calcs!F123 -> 371.09714 | G100: =Calcs!G123 -> 443.48421 | H100: =Calcs!H123 -> 511.04028 | I100: =Calcs!I123 -> 541.35131 | J100: =Calcs!J123 -> 510.16841 | K100: =Calcs!K123 -> 438.28559 | L100: =Calcs!L123 -> 357.82704 | ... S100: =Calcs!S123 -> 0
B101: Fixed Leg Basis (Notional x DF) | C101: [£'000] | E101: =Calcs!E124 -> 43183.428 | F101: =Calcs!F124 -> 39120.277 | G101: =Calcs!G124 -> 34898.181 | H101: =Calcs!H124 -> 30611.016 | I101: =Calcs!I124 -> 26344.483 | J101: =Calcs!J124 -> 22166.178 | K101: =Calcs!K124 -> 18093.06 | L101: =Calcs!L124 -> 14119.14 | ... S101: =Calcs!S124 -> 0
B103: Swap Rate (PV floating / PV notional) | C103: [%] | D103: =SUM(E100:S100)/SUM(E101:S101) -> 0.016381739
B104: All-in Fixed Cost of Debt (swap + 300bps margin) | C104: [%] | D104: =D103+Assumptions!$D$75 -> 0.046381739
B105: Memo: simple average of LIBOR over the tenor | C105: [%] | D105: =AVERAGE(Assumptions!E17:P17) -> 0.02077086
A108: =MAX($A$2:A107)+0.01 -> 4.05 | B108: Interest deductibility limitation
B110: EBITDA | C110: [£'000] | E110: =Calcs!E64 -> 8850.8784 | F110: =Calcs!F64 -> 8917.2135 | G110: =Calcs!G64 -> 8947.5974 | H110: =Calcs!H64 -> 8897.0806 | I110: =Calcs!I64 -> 8809.9226 | J110: =Calcs!J64 -> 8686.7658 | K110: =Calcs!K64 -> 8528.7406 | L110: =Calcs!L64 -> 8875.9078 | ... S110: =Calcs!S64 -> 803.14112
B111: Deductibility Cap (30% of EBITDA) | C111: [£'000] | E111: =Calcs!E133 -> 2655.2635 | F111: =Calcs!F133 -> 2675.1641 | G111: =Calcs!G133 -> 2684.2792 | H111: =Calcs!H133 -> 2669.1242 | I111: =Calcs!I133 -> 2642.9768 | J111: =Calcs!J133 -> 2606.0298 | K111: =Calcs!K133 -> 2558.6222 | L111: =Calcs!L133 -> 2662.7723 | ... S111: =Calcs!S133 -> 240.94233
B112: Total Financing Costs | C112: [£'000] | E112: =Calcs!E131 -> 2064.9084 | F112: =Calcs!F131 -> 1935.776 | G112: =Calcs!G131 -> 1893.4483 | H112: =Calcs!H131 -> 1848.3257 | I112: =Calcs!I131 -> 1761.5959 | J112: =Calcs!J131 -> 1598.613 | K112: =Calcs!K131 -> 1379.3092 | L112: =Calcs!L131 -> 1142.0819 | ... S112: =Calcs!S131 -> 0
B113: Headroom | C113: [£'000] | E113: =E111-E112 -> 590.35511 | F113: =F111-F112 -> 739.38804 | G113: =G111-G112 -> 790.83092 | H113: =H111-H112 -> 820.79847 | I113: =I111-I112 -> 881.38085 | J113: =J111-J112 -> 1007.4167 | K113: =K111-K112 -> 1179.313 | L113: =L111-L112 -> 1520.6904 | ... S113: =S111-S112 -> 240.94233
B114: Status | C114: [text] | E114: =IF(E113<0,"BINDING","headroom") -> headroom | F114: =IF(F113<0,"BINDING","headroom") -> headroom | G114: =IF(G113<0,"BINDING","headroom") -> headroom | H114: =IF(H113<0,"BINDING","headroom") -> headroom | I114: =IF(I113<0,"BINDING","headroom") -> headroom | J114: =IF(J113<0,"BINDING","headroom") -> headroom | K114: =IF(K113<0,"BINDING","headroom") -> headroom | L114: =IF(L113<0,"BINDING","headroom") -> headroom | ... S114: =IF(S113<0,"BINDING","headroom") -> headroom
B116: Minimum Headroom over the Debt Life | C116: [£'000] | D116: =MIN(E113:P113) -> 388.26254
B117: Minimum Headroom as % of the Cap | C117: [%] | D117: =D116/MIN(E111:P111) -> 0.68244388
B118: Senior Debt at which the Cap First Binds (2013) | C118: [£'000] | D118: =E111/(Assumptions!E80+Assumptions!$D$76/Assumptions!$D$74) -> 65892.649
B119: That Debt as % of Fixed Assets | C119: [%] | D119: =D118/Output!$D$76 -> 0.97618739
B120: Impact on the Bid Price | C120: [£'000] | D120: =IF($D$116>=0,0,"re-run with cap removed") -> 0
B122: The limitation costs nothing here because the DSCR test caps senior debt well below the level at which 30% of EBITDA becomes scarce. See the "Sensitivities" sheet for the price impact at tighter caps.
A125: =MAX($A$2:A124)+0.01 -> 4.06 | B125: Subordinated loan funding part of the investor's equity
B127: Coupon | C127: [%] | D127: =Assumptions!$D$85 -> 0.09
B128: Tenor | C128: [years] | D128: =Assumptions!$D$84 -> 5
B129: Minimum DSCR | C129: [x] | D129: =Assumptions!$D$86 -> 1.2
B130: Annuity Factor | C130: [x] | D130: =Assumptions!$D$87 -> 3.8896513
B131: Subordinated Loan Drawn | C131: [£'000] | D131: 6226.7708
B132: Annuity Payment | C132: [£'000] | D132: =D131/D130 -> 1600.8558
B134: Opening Balance | C134: [£'000] | E134: =IF(E$6<=$D$128,$D$131,0) -> 6226.7708 | F134: =IF(F$6<=$D$128,E137,0) -> 5186.3244 | G134: =IF(G$6<=$D$128,F137,0) -> 4052.2378 | H134: =IF(H$6<=$D$128,G137,0) -> 2816.0834 | I134: =IF(I$6<=$D$128,H137,0) -> 1468.6751 | J134: =IF(J$6<=$D$128,I137,0) -> 0 | K134: =IF(K$6<=$D$128,J137,0) -> 0 | L134: =IF(L$6<=$D$128,K137,0) -> 0 | M134: =IF(M$6<=$D$128,L137,0) -> 0 | ... S134: =IF(S$6<=$D$128,R137,0) -> 0
B135: Interest | C135: [£'000] | E135: =E134*$D$127 -> 560.40937 | F135: =F134*$D$127 -> 466.76919 | G135: =G134*$D$127 -> 364.7014 | H135: =H134*$D$127 -> 253.4475 | I135: =I134*$D$127 -> 132.18075 | J135: =J134*$D$127 -> 0 | K135: =K134*$D$127 -> 0 | L135: =L134*$D$127 -> 0 | ... S135: =S134*$D$127 -> 0
...

Sheet Sensitivities
A2: =Analysis!A2+1 -> 5 | B2: Project Storm - Sensitivities & Supporting Analysis
A4: =MAX($A$2:A3)+0.01 -> 5.01 | B4: Bid Price versus Target Equity Return [live]
B6: Target Equity IRR | C6: Equity Cheque | D6: Bid Price (equity) | E6: Implied EV | F6: EV per MW
B7: 0.1 | C7: =NPV($B7,Output!$E$46:$S$46) -> 16054.778 | D7: =C7+Calcs!$D$98-Calcs!$D$99-Assumptions!$D$92 -> 65772.407 | E7: =D7-Output!$D$74 -> 62272.407 | F7: =E7/Assumptions!$D$47 -> 1245.4481
B8: 0.105 | C8: =NPV($B8,Output!$E$46:$S$46) -> 15722.537 | D8: =C8+Calcs!$D$98-Calcs!$D$99-Assumptions!$D$92 -> 65440.166 | E8: =D8-Output!$D$74 -> 61940.166 | F8: =E8/Assumptions!$D$47 -> 1238.8033
B9: 0.11 | C9: =NPV($B9,Output!$E$46:$S$46) -> 15403.061 | D9: =C9+Calcs!$D$98-Calcs!$D$99-Assumptions!$D$92 -> 65120.69 | E9: =D9-Output!$D$74 -> 61620.69 | F9: =E9/Assumptions!$D$47 -> 1232.4138
B10: 0.115 | C10: =NPV($B10,Output!$E$46:$S$46) -> 15095.708 | D10: =C10+Calcs!$D$98-Calcs!$D$99-Assumptions!$D$92 -> 64813.337 | E10: =D10-Output!$D$74 -> 61313.337 | F10: =E10/Assumptions!$D$47 -> 1226.2667
B11: 0.12 | C11: =NPV($B11,Output!$E$46:$S$46) -> 14799.873 | D11: =C11+Calcs!$D$98-Calcs!$D$99-Assumptions!$D$92 -> 64517.503 | E11: =D11-Output!$D$74 -> 61017.503 | F11: =E11/Assumptions!$D$47 -> 1220.3501
B12: 0.125 | C12: =NPV($B12,Output!$E$46:$S$46) -> 14514.99 | D12: =C12+Calcs!$D$98-Calcs!$D$99-Assumptions!$D$92 -> 64232.619 | E12: =D12-Output!$D$74 -> 60732.619 | F12: =E12/Assumptions!$D$47 -> 1214.6524
B13: 0.13 | C13: =NPV($B13,Output!$E$46:$S$46) -> 14240.52 | D13: =C13+Calcs!$D$98-Calcs!$D$99-Assumptions!$D$92 -> 63958.15 | E13: =D13-Output!$D$74 -> 60458.15 | F13: =E13/Assumptions!$D$47 -> 1209.163
B14: 0.14 | C14: =NPV($B14,Output!$E$46:$S$46) -> 13720.838 | D14: =C14+Calcs!$D$98-Calcs!$D$99-Assumptions!$D$92 -> 63438.468 | E14: =D14-Output!$D$74 -> 59938.468 | F14: =E14/Assumptions!$D$47 -> 1198.7694
B16: The bid price barely moves across a 400bp range of target returns: only c.£2.3m separates a 10% and a 14% hurdle. Because the equity cheque is a thin slice of the price, discipline on debt sizing matters far more than discipline on the hurdle rate.
A19: =MAX($A$2:A18)+0.01 -> 5.02 | B19: Equity IRR at the Recommended Price - Operating Scenarios
B21: Scenario | C21: Equity IRR | D21: Minimum DSCR | E21: How to reproduce
B22: Base case (P75, base power price) | C22: 0.12 | D22: 1.3 | E22: Assumptions!D50 = 1
B23: P90 for 10 years, then P75 | C23: 0.0689 | D23: 1.21 | E23: Assumptions!D50 = 3
B24: P90 in every year | C24: 0.0595 | D24: 1.09 | E24: Assumptions!D50 = 2
B25: Power price -5% | C25: 0.0867 | D25: 1.1 | E25: Scale Calcs row 49 by 0.95
B26: Power price -10% | C26: 0.0476 | D26: 0.89 | E26: Scale Calcs row 49 by 0.90
B27: Power price +10% | C27: 0.1773 | D27: 1.37 | E27: Scale Calcs row 49 by 1.10
B28: Operating costs +10% | C28: 0.0833 | D28: 1.02 | E28: Assumptions!D62 = 55, D63 = 5.5
B29: Power price -10% and P90 throughout | C29: -0.0349 | D29: 0.7 | E29: Both of the above
B31: Values are produced by flexing the input cells named in the final column and reading Output!D57 and the DSCR row. They are pasted here as inputs so that the whole grid can be seen at once.
B32: Read-across: at 84% gearing the equity is highly geared to the power price. A 10% price shortfall alone takes DSCR below 1.00x - a payment default, not merely a covenant breach.
A35: =MAX($A$2:A34)+0.01 -> 5.03 | B35: Bid Price at Tighter Interest Deductibility Caps
B37: Cap (% of EBITDA) | C37: Senior Debt | D37: Bid Price | E37: Change vs Base
B38: No limit | C38: 51242 | D38: 64518 | E38: 0
B39: 30% (base assumption) | C39: 51242 | D39: 64518 | E39: 0
B40: 25% | C40: 51242 | D40: 64518 | E40: 0
B41: 20% | C41: 51222 | D41: 64485 | E41: -32
B42: 15% | C42: 50856 | D42: 64032 | E42: -486
B43: 10% | C43: 50190 | D43: 63236 | E43: -1281
B44: 5% | C44: 49525 | D44: 62441 | E44: -2077
B45: Nil deduction | C45: 48859 | D45: 61646 | E45: -2872
B47: The 30% cap is worth nothing at this leverage. It would only start to bite at roughly £65.9m of senior debt - about 98% of fixed assets - which the DSCR test rules out long before the tax rule does.
A50: =MAX($A$2:A49)+0.01 -> 5.04 | B50: Financial Impact of a PPA
B52: A fixed-price PPA on the merchant element, priced at a discount to the forward curve, in exchange for a lower DSCR floor from the banks.
B54: Bid price at a 12% equity IRR
B55: PPA discount to the curve | C55: DSCR floor 1.30x (merchant) | D55: DSCR floor 1.20x | E55: DSCR floor 1.15x
B56: 0% (curve) | C56: 64518 | D56: 65926 | E56: 66438
B57: 5% | C57: 62014 | D57: 63362 | E57: 64128
B58: 10% | C58: 59510 | D58: 60798 | E58: 61530
B59: 15% | C59: 57006 | D59: 58234 | E59: 58932
B61: Senior debt raised
B62: PPA discount to the curve | C62: DSCR floor 1.30x (merchant) | D62: DSCR floor 1.20x | E62: DSCR floor 1.15x
B63: 0% (curve) | C63: 51242 | D63: 55737 | E63: 57375
B64: 5% | C64: 49273 | D64: 53594 | E64: 56051
B65: 10% | C65: 47304 | D65: 51451 | E65: 53809
B66: 15% | C66: 45334 | D66: 49308 | E66: 51567
B68: The trade is a real one: a 1.30x to 1.15x relaxation is worth about £6.1m of extra debt and £1.9m of extra price, which pays for a PPA discount of just under 4%. Beyond that the discount costs more than the leverage is worth.
A71: =MAX($A$2:A70)+0.01 -> 5.05 | B71: Revenue Mix - Merchant versus Contracted [live]
B73: Year | C73: Merchant | D73: Subsidy | E73: Total | F73: Merchant %
B74: =Output!E$5 -> 2013 | C74: =Output!E12 -> 7011.8159 | D74: =Output!E13 -> 5050 | E74: =Output!E14 -> 12061.816 | F74: =C74/E74 -> 0.58132341
B75: =Output!F$5 -> 2014 | C75: =Output!F12 -> 7115.9518 | D75: =Output!F13 -> 5100.5 | E75: =Output!F14 -> 12216.452 | F75: =C75/E75 -> 0.58248925
B76: =Output!G$5 -> 2015 | C76: =Output!G12 -> 7186.0597 | D76: =Output!G13 -> 5151.505 | E76: =Output!G14 -> 12337.565 | F76: =C76/E76 -> 0.58245366
B77: =Output!H$5 -> 2016 | C77: =Output!H12 -> 7186.0597 | D77: =Output!H13 -> 5177.2625 | E77: =Output!H14 -> 12363.322 | F77: =C77/E77 -> 0.58124019
B78: =Output!I$5 -> 2017 | C78: =Output!I12 -> 7151.0058 | D78: =Output!I13 -> 5203.1488 | E78: =Output!I14 -> 12354.155 | F78: =C78/E78 -> 0.57883408
B79: =Output!J$5 -> 2018 | C79: =Output!J12 -> 7081.5785 | D79: =Output!J13 -> 5229.1646 | E79: =Output!J14 -> 12310.743 | F79: =C79/E79 -> 0.57523567
B80: =Output!K$5 -> 2019 | C80: =Output!K12 -> 6978.9469 | D80: =Output!K13 -> 5255.3104 | E80: =Output!K14 -> 12234.257 | F80: =C80/E80 -> 0.57044304
B81: =Output!L$5 -> 2020 | C81: =Output!L12 -> 7383.2117 | D81: =Output!L13 -> 5281.587 | E81: =Output!L14 -> 12664.799 | F81: =C81/E81 -> 0.58297111
B82: =Output!M$5 -> 2021 | C82: =Output!M12 -> 7681.4934 | D82: =Output!M13 -> 5307.9949 | E82: =Output!M14 -> 12989.488 | F82: =C82/E82 -> 0.59136228
B83: =Output!N$5 -> 2022 | C83: =Output!N12 -> 6490.1014 | D83: =Output!N13 -> 5334.5349 | E83: =Output!N14 -> 11824.636 | F83: =C83/E83 -> 0.54886267
B84: =Output!O$5 -> 2023 | C84: =Output!O12 -> 6274.79 | D84: =Output!O13 -> 0 | E84: =Output!O14 -> 6274.79 | F84: =C84/E84 -> 1
B85: =Output!P$5 -> 2024 | C85: =Output!P12 -> 6038.0055 | D85: =Output!P13 -> 0 | E85: =Output!P14 -> 6038.0055 | F85: =C85/E85 -> 1
B86: =Output!Q$5 -> 2025 | C86: =Output!Q12 -> 5782.8785 | D86: =Output!Q13 -> 0 | E86: =Output!Q14 -> 5782.8785 | F86: =C86/E86 -> 1
B87: =Output!R$5 -> 2026 | C87: =Output!R12 -> 5512.6505 | D87: =Output!R13 -> 0 | E87: =Output!R14 -> 5512.6505 | F87: =C87/E87 -> 1
B88: =Output!S$5 -> 2027 | C88: =Output!S12 -> 5230.6079 | D88: =Output!S13 -> 0 | E88: =Output!S14 -> 5230.6079 | F88: =C88/E88 -> 1
B90: The subsidy expires at the end of 2022, 15 years after commissioning. From 2023 the project is fully merchant and EBITDA falls by roughly 70%, which is why the debt has to be gone by 2024.
A93: =MAX($A$2:A92)+0.01 -> 5.06 | B93: Negotiating Range [live]
B95: Walk-away price at a 12% IRR | D95: =Output!$D$52 -> 64517.503
B96: Price at an 11% IRR (the level an infrastructure fund would pay) | D96: =NPV(0.11,Output!$E$46:$S$46)+Calcs!$D$98-Calcs!$D$99-Assumptions!$D$92 -> 65120.69
B97: Vendor's carrying value of the equity | D97: =Output!$D$83 -> 71900
B98: Loss to vendor against carrying value at our price | D98: =D97-D95 -> 7382.4973
B99: That loss as a share of carrying value | D99: =D98/D97 -> 0.10267729
B101: The vendor must close by 31 December and has failed to raise project finance. We should open materially below the walk-away price and hold £64.5m in reserve as the ceiling.
